Workbook

Sheet Build Status
A1: Akki OS — Build Status
A2: 20 September 2026 (refresh)
A4: 1 — What We're Building
A6: Component | B6: What it does | D6: Reqs
A7: Akki OS core | B7: Six engines (SyniSense, Solva, Northena, Mtafiti, Targeta, Mkondo) + the Watch + the Ledger — the governed platform. Docs 1–20 and extensions. | D7: 286
A8: Rules Service | B8: The Policy Administration Point — rule authoring, ceremony, adoption, the Registry. | D8: 27
A9: DAP | B9: External-party acquisition portal built on Akki — browse, connect, extract, fine-tune, download. | D9: 30
A10: Security hardening | B10: Assurance promises (Watch conduct) plus Trojan/whisper amendments (artefact and output-content threats). | D10: 35
A11: Governance Architecture | B11: The standard (Part 1) everything above is measured against, translated into per-component build targets (Part 2). | D11: 41
A12: Agent & Swarm Containment | B12: Contains a lab's own deployed agent(s) — capability ceilings, earned scope, coalition bounding. Governance model only; integration layer explicitly out of scope. | D12: 12
A14: Total, defined and buildable today | D14: 589
A15: Refreshed 18 Sep 2026: +47 (SEC, DET, FP, TD, HR, BC, DAP-37/38, serving integrity, watch learning, S-26–S-29). Previous baseline 431 / 444 rows.
A16: Refreshed 20 Sep 2026: +73 (ENT-1–49 entitlement; MEM-1–11 memory compaction; PRIN-1–13 principal model). Previous total 478.
A17: Refreshed 20 Sep 2026 (b): +31 (CON-1–31 content registry). Previous total 551.
A19: Gap | B19: State
A20: G-1 — No enumerated Trusted Computing Base | B20: OPEN
A21: G-2 — No architecture description | B21: OPEN
A22: G-3 — Asset inventory covers estate sources only | B22: PARTIAL — DAP-1/2 close it for external parties
A23: G-4 — No assessment procedure on any base rule | B23: OPEN
A24: G-5 — Checkpoint roles named only for the Watch | B24: PARTIAL — DAP §4 names them for every DAP operation
A25: G-6 — No security architecture description | B25: PARTIAL — Watch confirmed to meet all 3 reference-monitor properties; not yet written up
A26: G-7 — No named SFPs; lower-the-standard is subject-alterable | B26: OPEN — ruling pending (R-2)
A27: G-8 — Receipt omits identity, timestamp | B27: SPEC-CLOSED — Security_Promise_Set_Amendments Amendment 3. Not built.
A28: G-9 — No change-control procedure for system rules | B28: SPEC-CLOSED — Rules Service RBM-7/RBM-8. Not built.
A29: G-10 — No determinism inventory | B29: OPEN
A30: G-11 — No failure-type enumeration | B30: PARTIAL — DAP-28/29/30 specify it for DAP; not platform-wide
... A36: Rules Service implementation (builder's audit) | B36: Nothing built — spec complete, code not started
A39: 3 — Missing Requirements — Fully Open, No Spec Yet
A41: — TCB Enumeration — apply Attribute 1's test to every Doc 0 component, publish the list (closes G-1)
A42: — Security Architecture Description — ADV_ARC-style write-up for MOAC, distance gate, format gate (closes G-6 fully)
A43: — Named Security Function Policies + the lower-the-standard ruling (closes G-7)
A44: — Determinism Inventory — classify every component deterministic/learned in one place, map to EU AI Act Art. 14 (closes G-10)
A45: — Failure Posture Enumeration — platform-wide, not only DAP's slice (closes G-11 fully)
A46: — Trust Domain Description + deployment-model ruling, general case (closes G-12 fully)
A47: — Hand-off Generalisation spec for Mkondo (closes G-13)
A48: — Business Continuity Annex
A49: — Pruning & Unlearning Amendment (DAP-37/38, S-26)
A52: 4 — Generate Next
A54: Say which, and it's the next document built. Recommended first: TCB Enumeration + Security Architecture Description — both foundational, both referenced by other open gaps (G-2, G-5, G-6, G-10 all depend on one or both existing first).
A56: Full requirement-level detail, every ID, every citation: the System Rules Registry sheet.

Sheet Audit Summary
A1: Akki OS — Audit Summary
A2: Every figure is a formula over QA Verification and Check Register. Nothing is entered here.
A4: Rule verdicts by weight | B4: COUNTS | C4: UNRATIFIED | D4: OPEN | E4: UNDEFINED | F4: All
A5: PASS | B5: =COUNTIFS('QA Verification'!$H$2:$H$603,$A5,'QA Verification'!$L$2:$L$603,B$4) | C5: =COUNTIFS('QA Verification'!$H$2:$H$603,$A5,'QA Verification'!$L$2:$L$603,C$4) | D5: =COUNTIFS('QA Verification'!$H$2:$H$603,$A5,'QA Verification'!$L$2:$L$603,D$4) | E5: =COUNTIFS('QA Verification'!$H$2:$H$603,$A5,'QA Verification'!$L$2:$L$603,E$4) | F5: =SUM(B5:E5)
A6: FAIL | B6: =COUNTIFS('QA Verification'!$H$2:$H$603,$A6,'QA Verification'!$L$2:$L$603,B$4) | C6: =COUNTIFS('QA Verification'!$H$2:$H$603,$A6,'QA Verification'!$L$2:$L$603,C$4) | D6: =COUNTIFS('QA Verification'!$H$2:$H$603,$A6,'QA Verification'!$L$2:$L$603,D$4) | E6: =COUNTIFS('QA Verification'!$H$2:$H$603,$A6,'QA Verification'!$L$2:$L$603,E$4) | F6: =SUM(B6:E6)
A7: NOT BUILT | B7: =COUNTIFS('QA Verification'!$H$2:$H$603,$A7,'QA Verification'!$L$2:$L$603,B$4) | C7: =COUNTIFS('QA Verification'!$H$2:$H$603,$A7,'QA Verification'!$L$2:$L$603,C$4) | D7: =COUNTIFS('QA Verification'!$H$2:$H$603,$A7,'QA Verification'!$L$2:$L$603,D$4) | E7: =COUNTIFS('QA Verification'!$H$2:$H$603,$A7,'QA Verification'!$L$2:$L$603,E$4) | F7: =SUM(B7:E7)
A8: NOT VERIFIABLE | B8: =COUNTIFS('QA Verification'!$H$2:$H$603,$A8,'QA Verification'!$L$2:$L$603,B$4) | C8: =COUNTIFS('QA Verification'!$H$2:$H$603,$A8,'QA Verification'!$L$2:$L$603,C$4) | D8: =COUNTIFS('QA Verification'!$H$2:$H$603,$A8,'QA Verification'!$L$2:$L$603,D$4) | E8: =COUNTIFS('QA Verification'!$H$2:$H$603,$A8,'QA Verification'!$L$2:$L$603,E$4) | F8: =SUM(B8:E8)
A9: NOT EXAMINED | B9: =COUNTIFS('QA Verification'!$H$2:$H$603,$A9,'QA Verification'!$L$2:$L$603,B$4) | C9: =COUNTIFS('QA Verification'!$H$2:$H$603,$A9,'QA Verification'!$L$2:$L$603,C$4) | D9: =COUNTIFS('QA Verification'!$H$2:$H$603,$A9,'QA Verification'!$L$2:$L$603,D$4) | E9: =COUNTIFS('QA Verification'!$H$2:$H$603,$A9,'QA Verification'!$L$2:$L$603,E$4) | F9: =SUM(B9:E9)
A10: (no verdict yet) | B10: =COUNTIFS('QA Verification'!$H$2:$H$603,"",'QA Verification'!$L$2:$L$603,B$4) | C10: =COUNTIFS('QA Verification'!$H$2:$H$603,"",'QA Verification'!$L$2:$L$603,C$4) | D10: =COUNTIFS('QA Verification'!$H$2:$H$603,"",'QA Verification'!$L$2:$L$603,D$4) | E10: =COUNTIFS('QA Verification'!$H$2:$H$603,"",'QA Verification'!$L$2:$L$603,E$4) | F10: =SUM(B10:E10)
A11: Total | B11: =SUM(B5:B10) | C11: =SUM(C5:C10) | D11: =SUM(D5:D10) | E11: =SUM(E5:E10) | F11: =SUM(F5:F10)
A13: Examination load | B13: Rules
A14: Effective Tier A — examined in full | B14: =COUNTIF('QA Verification'!$R$2:$R$603,"A*")
A15: Effective Tier B — sampled ≥ 30% per document | B15: =COUNTIF('QA Verification'!$R$2:$R$603,"B*")
A16: Weight COUNTS held at V7 by the v1 heading derivation and not raised by §6 | B16: =COUNTIFS('QA Verification'!$L$2:$L$603,"COUNTS",'QA Verification'!$P$2:$P$603,"V7")
A17: Rows whose class is PROVISIONAL (derive from rule text before relying on it) | B17: =COUNTIF('QA Verification'!$Q$2:$Q$603,"*PROVISIONAL*")
A18: Rows with status UNDEFINED awaiting owner ruling | B18: =COUNTIF('QA Verification'!$K$2:$K$603,"UNDEFINED")
A19: FAIL by severity — S1 | B19: =COUNTIFS('QA Verification'!$H$2:$H$603,"FAIL",'QA Verification'!$T$2:$T$603,"S1")
A20: FAIL by severity — S2 | B20: =COUNTIFS('QA Verification'!$H$2:$H$603,"FAIL",'QA Verification'!$T$2:$T$603,"S2")
A21: FAIL by severity — S3 | B21: =COUNTIFS('QA Verification'!$H$2:$H$603,"FAIL",'QA Verification'!$T$2:$T$603,"S3")
A22: FAIL by severity — S4 | B22: =COUNTIFS('QA Verification'!$H$2:$H$603,"FAIL",'QA Verification'!$T$2:$T$603,"S4")
A23: FAIL recorded without a severity (record defect) | B23: =COUNTIFS('QA Verification'!$H$2:$H$603,"FAIL",'QA Verification'!$T$2:$T$603,"")
A24: NOT EXAMINED recorded without a reason (record defect) | B24: =COUNTIFS('QA Verification'!$H$2:$H$603,"NOT EXAMINED",'QA Verification'!$W$2:$W$603,"")
A26: Check Register | B26: Count
A27: PASS | B27: =COUNTIF('Check Register'!$J$2:$J$181,A27)
A28: FAIL | B28: =COUNTIF('Check Register'!$J$2:$J$181,A28)
A29: NOT BUILT | B29: =COUNTIF('Check Register'!$J$2:$J$181,A29)
A30: NOT VERIFIABLE | B30: =COUNTIF('Check Register'!$J$2:$J$181,A30)
A31: SOUND | B31: =COUNTIF('Check Register'!$J$2:$J$181,A31)
A32: DEFECT | B32: =COUNTIF('Check Register'!$J$2:$J$181,A32)
A33: NOT ASSESSABLE | B33: =COUNTIF('Check Register'!$J$2:$J$181,A33)
A34: (no verdict yet) | B34: =COUNTBLANK('Check Register'!$J$2:$J$181)

Sheet QA Verification
A1: Rule ID | B1: Doc | C1: Status | D1: Primary verification class | E1: Secondary class | F1: Evidence required (primary) | G1: Sampling tier | H1: Auditor verdict | I1: Evidence examined (ref) | J1: Finding ref | K1: Normalised status | L1: Weight | M1: Statement basis | N1: §6 check ID(s) | O1: §6 class(es) — governs | P1: Effective class | Q1: Class basis | R1: Effective tier | S1: Observed (stated without evaluation) | T1: Severity (FAIL only) | U1: Commit · ratchet | V1: Rule-text quality (Part 0) | W1: NOT EXAMINED reason | X1: Reviewer re-performance
A2: A5.1 | B2: Doc 1 | C2: CANON | D2: V7 — Document & design inspection | F2: Specification text against implementation description; provenance sections; objective card lines | G2: A — 100% | K2: =IFERROR(INDEX('Status Map'!$B$2:$B$12,MATCH(C2,'Status Map'!$A$2:$A$12,0)),"UNDEFINED") | L2: =IFERROR(INDEX('Status Map'!$C$2:$C$12,MATCH(C2,'Status Map'!$A$2:$A$12,0)),"UNDEFINED") | M2: HEADING ONLY | N2: C-6.3.1 | O2: V2 | P2: =IF(O2<>"",O2,LEFT(D2,2)) | Q2: =IF(O2<>"","Standards §6",IF(M2="HEADING ONLY","Derived from heading — PROVISIONAL",IF(M2="TEXT NOT IN REGISTRY","No text to derive from — PROVISIONAL","Derived from registered statement"))) | R2: =IF(OR(LEFT(G2,1)="A",L2="COUNTS",ISNUMBER(SEARCH("V1",P2)),ISNUMBER(SEARCH("V2",P2)),ISNUMBER(SEARCH("V5",P2))),"A — 100%","B — sample ≥ 30%")
A3: A5.2 | B3: Doc 1 | C3: CANON | D3: V7 — Document & design inspection | F3: Specification text against implementation description; provenance sections; objective card lines | G3: A — 100% | K3: =IFERROR(INDEX('Status Map'!$B$2:$B$12,MATCH(C3,'Status Map'!$A$2:$A$12,0)),"UNDEFINED") | L3: =IFERROR(INDEX('Status Map'!$C$2:$C$12,MATCH(C3,'Status Map'!$A$2:$A$12,0)),"UNDEFINED") | M3: HEADING ONLY | P3: =IF(O3<>"",O3,LEFT(D3,2)) | Q3: =IF(O3<>"","Standards §6",IF(M3="HEADING ONLY","Derived from heading — PROVISIONAL",IF(M3="TEXT NOT IN REGISTRY","No text to derive from — PROVISIONAL","Derived from registered statement"))) | R3: =IF(OR(LEFT(G3,1)="A",L3="COUNTS",ISNUMBER(SEARCH("V1",P3)),ISNUMBER(SEARCH("V2",P3)),ISNUMBER(SEARCH("V5",P3))),"A — 100%","B — sample ≥ 30%")
A4: A5.3 | B4: Doc 1 | C4: CANON | D4: V7 — Document & design inspection | F4: Specification text against implementation description; provenance sections; objective card lines | G4: A — 100% | K4: =IFERROR(INDEX('Status Map'!$B$2:$B$12,MATCH(C4,'Status Map'!$A$2:$A$12,0)),"UNDEFINED") | L4: =IFERROR(INDEX('Status Map'!$C$2:$C$12,MATCH(C4,'Status Map'!$A$2:$A$12,0)),"UNDEFINED") | M4: HEADING ONLY | P4: =IF(O4<>"",O4,LEFT(D4,2)) | Q4: =IF(O4<>"","Standards §6",IF(M4="HEADING ONLY","Derived from heading — PROVISIONAL",IF(M4="TEXT NOT IN REGISTRY","No text to derive from — PROVISIONAL","Derived from registered statement"))) | R4: =IF(OR(LEFT(G4,1)="A",L4="COUNTS",ISNUMBER(SEARCH("V1",P4)),ISNUMBER(SEARCH("V2",P4)),ISNUMBER(SEARCH("V5",P4))),"A — 100%","B — sample ≥ 30%")
A5: A5.4 | B5: Doc 1 | C5: CANON | D5: V7 — Document & design inspection | F5: Specification text against implementation description; provenance sections; objective card lines | G5: A — 100% | K5: =IFERROR(INDEX('Status Map'!$B$2:$B$12,MATCH(C5,'Status Map'!$A$2:$A$12,0)),"UNDEFINED") | L5: =IFERROR(INDEX('Status Map'!$C$2:$C$12,MATCH(C5,'Status Map'!$A$2:$A$12,0)),"UNDEFINED") | M5: HEADING ONLY | P5: =IF(O5<>"",O5,LEFT(D5,2)) | Q5: =IF(O5<>"","Standards §6",IF(M5="HEADING ONLY","Derived from heading — PROVISIONAL",IF(M5="TEXT NOT IN REGISTRY","No text to derive from — PROVISIONAL","Derived from registered statement"))) | R5: =IF(OR(LEFT(G5,1)="A",L5="COUNTS",ISNUMBER(SEARCH("V1",P5)),ISNUMBER(SEARCH("V2",P5)),ISNUMBER(SEARCH("V5",P5))),"A — 100%","B — sample ≥ 30%")
A6: A5.5 | B6: Doc 1 | C6: CANON | D6: V7 — Document & design inspection | F6: Specification text against implementation description; provenance sections; objective card lines | G6: A — 100% | K6: =IFERROR(INDEX('Status Map'!$B$2:$B$12,MATCH(C6,'Status Map'!$A$2:$A$12,0)),"UNDEFINED") | L6: =IFERROR(INDEX('Status Map'!$C$2:$C$12,MATCH(C6,'Status Map'!$A$2:$A$12,0)),"UNDEFINED") | M6: HEADING ONLY | P6: =IF(O6<>"",O6,LEFT(D6,2)) | Q6: =IF(O6<>"","Standards §6",IF(M6="HEADING ONLY","Derived from heading — PROVISIONAL",IF(M6="TEXT NOT IN REGISTRY","No text to derive from — PROVISIONAL","Derived from registered statement"))) | R6: =IF(OR(LEFT(G6,1)="A",L6="COUNTS",ISNUMBER(SEARCH("V1",P6)),ISNUMBER(SEARCH("V2",P6)),ISNUMBER(SEARCH("V5",P6))),"A — 100%","B — sample ≥ 30%")
A7: A5.6 | B7: Doc 1 | C7: CANON | D7: V7 — Document & design inspection | F7: Specification text against implementation description; provenance sections; objective card lines | G7: A — 100% | K7: =IFERROR(INDEX('Status Map'!$B$2:$B$12,MATCH(C7,'Status Map'!$A$2:$A$12,0)),"UNDEFINED") | L7: =IFERROR(INDEX('Status Map'!$C$2:$C$12,MATCH(C7,'Status Map'!$A$2:$A$12,0)),"UNDEFINED") | M7: HEADING ONLY | P7: =IF(O7<>"",O7,LEFT(D7,2)) | Q7: =IF(O7<>"","Standards §6",IF(M7="HEADING ONLY","Derived from heading — PROVISIONAL",IF(M7="TEXT NOT IN REGISTRY","No text to derive from — PROVISIONAL","Derived from registered statement"))) | R7: =IF(OR(LEFT(G7,1)="A",L7="COUNTS",ISNUMBER(SEARCH("V1",P7)),ISNUMBER(SEARCH("V2",P7)),ISNUMBER(SEARCH("V5",P7))),"A — 100%","B — sample ≥ 30%")
A8: A5.7 | B8: Doc 1 | C8: CANON | D8: V3 — Record evidence | F8: Ledger rows inspected; hash-chain verifier receipt; refused operations present on identical terms | G8: A — 100% | K8: =IFERROR(INDEX('Status Map'!$B$2:$B$12,MATCH(C8,'Status Map'!$A$2:$A$12,0)),"UNDEFINED") | L8: =IFERROR(INDEX('Status Map'!$C$2:$C$12,MATCH(C8,'Status Map'!$A$2:$A$12,0)),"UNDEFINED") | M8: HEADING ONLY | N8: C-6.3.6 | O8: V3 | P8: =IF(O8<>"",O8,LEFT(D8,2)) | Q8: =IF(O8<>"","Standards §6",IF(M8="HEADING ONLY","Derived from heading — PROVISIONAL",IF(M8="TEXT NOT IN REGISTRY","No text to derive from — PROVISIONAL","Derived from registered statement"))) | R8: =IF(OR(LEFT(G8,1)="A",L8="COUNTS",ISNUMBER(SEARCH("V1",P8)),ISNUMBER(SEARCH("V2",P8)),ISNUMBER(SEARCH("V5",P8))),"A — 100%","B — sample ≥ 30%")
A9: A5.8 | B9: Doc 1 | C9: CANON | D9: V3 — Record evidence | F9: Ledger rows inspected; hash-chain verifier receipt; refused operations present on identical terms | G9: A — 100% | K9: =IFERROR(INDEX('Status Map'!$B$2:$B$12,MATCH(C9,'Status Map'!$A$2:$A$12,0)),"UNDEFINED") | L9: =IFERROR(INDEX('Status Map'!$C$2:$C$12,MATCH(C9,'Status Map'!$A$2:$A$12,0)),"UNDEFINED") | M9: HEADING ONLY | P9: =IF(O9<>"",O9,LEFT(D9,2)) | Q9: =IF(O9<>"","Standards §6",IF(M9="HEADING ONLY","Derived from heading — PROVISIONAL",IF(M9="TEXT NOT IN REGISTRY","No text to derive from — PROVISIONAL","Derived from registered statement"))) | R9: =IF(OR(LEFT(G9,1)="A",L9="COUNTS",ISNUMBER(SEARCH("V1",P9)),ISNUMBER(SEARCH("V2",P9)),ISNUMBER(SEARCH("V5",P9))),"A — 100%","B — sample ≥ 30%")
A10: A5.9 | B10: Doc 1 | C10: CANON | D10: V5 — Failure-injection demonstration | F10: Dependency made unreachable or check made to error; observed refusal; no result returned; stale marker where degradation is the ruled posture | G10: A — 100% | K10: =IFERROR(INDEX('Status Map'!$B$2:$B$12,MATCH(C10,'Status Map'!$A$2:$A$12,0)),"UNDEFINED") | L10: =IFERROR(INDEX('Status Map'!$C$2:$C$12,MATCH(C10,'Status Map'!$A$2:$A$12,0)),"UNDEFINED") | M10: HEADING ONLY | P10: =IF(O10<>"",O10,LEFT(D10,2)) | Q10: =IF(O10<>"","Standards §6",IF(M10="HEADING ONLY","Derived from heading — PROVISIONAL",IF(M10="TEXT NOT IN REGISTRY","No text to derive from — PROVISIONAL","Derived from registered statement"))) | R10: =IF(OR(LEFT(G10,1)="A",L10="COUNTS",ISNUMBER(SEARCH("V1",P10)),ISNUMBER(SEARCH("V2",P10)),ISNUMBER(SEARCH("V5",P10))),"A — 100%","B — sample ≥ 30%")
A11: A5.1 | B11: Doc 2 | C11: CANON | D11: V7 — Document & design inspection | F11: Specification text against implementation description; provenance sections; objective card lines | G11: B — sample ≥ 30% | K11: =IFERROR(INDEX('Status Map'!$B$2:$B$12,MATCH(C11,'Status Map'!$A$2:$A$12,0)),"UNDEFINED") | L11: =IFERROR(INDEX('Status Map'!$C$2:$C$12,MATCH(C11,'Status Map'!$A$2:$A$12,0)),"UNDEFINED") | M11: HEADING ONLY | P11: =IF(O11<>"",O11,LEFT(D11,2)) | Q11: =IF(O11<>"","Standards §6",IF(M11="HEADING ONLY","Derived from heading — PROVISIONAL",IF(M11="TEXT NOT IN REGISTRY","No text to derive from — PROVISIONAL","Derived from registered statement"))) | R11: =IF(OR(LEFT(G11,1)="A",L11="COUNTS",ISNUMBER(SEARCH("V1",P11)),ISNUMBER(SEARCH("V2",P11)),ISNUMBER(SEARCH("V5",P11))),"A — 100%","B — sample ≥ 30%")
A12: A5.2 | B12: Doc 2 | C12: PROPOSED | D12: V7 — Document & design inspection | F12: Specification text against implementation description; provenance sections; objective card lines | G12: B — sample ≥ 30% | K12: =IFERROR(INDEX('Status Map'!$B$2:$B$12,MATCH(C12,'Status Map'!$A$2:$A$12,0)),"UNDEFINED") | L12: =IFERROR(INDEX('Status Map'!$C$2:$C$12,MATCH(C12,'Status Map'!$A$2:$A$12,0)),"UNDEFINED") | M12: HEADING ONLY | P12: =IF(O12<>"",O12,LEFT(D12,2)) | Q12: =IF(O12<>"","Standards §6",IF(M12="HEADING ONLY","Derived from heading — PROVISIONAL",IF(M12="TEXT NOT IN REGISTRY","No text to derive from — PROVISIONAL","Derived from registered statement"))) | R12: =IF(OR(LEFT(G12,1)="A",L12="COUNTS",ISNUMBER(SEARCH("V1",P12)),ISNUMBER(SEARCH("V2",P12)),ISNUMBER(SEARCH("V5",P12))),"A — 100%","B — sample ≥ 30%")
A13: A5.3 | B13: Doc 2 | C13: — | D13: V7 — Document & design inspection | F13: Specification text against implementation description; provenance sections; objective card lines | G13: B — sample ≥ 30% | K13: =IFERROR(INDEX('Status Map'!$B$2:$B$12,MATCH(C13,'Status Map'!$A$2:$A$12,0)),"UNDEFINED") | L13: =IFERROR(INDEX('Status Map'!$C$2:$C$12,MATCH(C13,'Status Map'!$A$2:$A$12,0)),"UNDEFINED") | M13: HEADING ONLY | P13: =IF(O13<>"",O13,LEFT(D13,2)) | Q13: =IF(O13<>"","Standards §6",IF(M13="HEADING ONLY","Derived from heading — PROVISIONAL",IF(M13="TEXT NOT IN REGISTRY","No text to derive from — PROVISIONAL","Derived from registered statement"))) | R13: =IF(OR(LEFT(G13,1)="A",L13="COUNTS",ISNUMBER(SEARCH("V1",P13)),ISNUMBER(SEARCH("V2",P13)),ISNUMBER(SEARCH("V5",P13))),"A — 100%","B — sample ≥ 30%")
A14: A5.4 | B14: Doc 2 | C14: CANON | D14: V4 — Governance-record evidence | F14: DECISIONS.md entry; ceremony record with tier, countersign, countdown, apply, re-verify; canon_ref present | G14: B — sample ≥ 30% | K14: =IFERROR(INDEX('Status Map'!$B$2:$B$12,MATCH(C14,'Status Map'!$A$2:$A$12,0)),"UNDEFINED") | L14: =IFERROR(INDEX('Status Map'!$C$2:$C$12,MATCH(C14,'Status Map'!$A$2:$A$12,0)),"UNDEFINED") | M14: HEADING ONLY | P14: =IF(O14<>"",O14,LEFT(D14,2)) | Q14: =IF(O14<>"","Standards §6",IF(M14="HEADING ONLY","Derived from heading — PROVISIONAL",IF(M14="TEXT NOT IN REGISTRY","No text to derive from — PROVISIONAL","Derived from registered statement"))) | R14: =IF(OR(LEFT(G14,1)="A",L14="COUNTS",ISNUMBER(SEARCH("V1",P14)),ISNUMBER(SEARCH("V2",P14)),ISNUMBER(SEARCH("V5",P14))),"A — 100%","B — sample ≥ 30%")
A15: A5.5 | B15: Doc 2 | C15: CANON | D15: V7 — Document & design inspection | F15: Specification text against implementation description; provenance sections; objective card lines | G15: B — sample ≥ 30% | K15: =IFERROR(INDEX('Status Map'!$B$2:$B$12,MATCH(C15,'Status Map'!$A$2:$A$12,0)),"UNDEFINED") | L15: =IFERROR(INDEX('Status Map'!$C$2:$C$12,MATCH(C15,'Status Map'!$A$2:$A$12,0)),"UNDEFINED") | M15: HEADING ONLY | P15: =IF(O15<>"",O15,LEFT(D15,2)) | Q15: =IF(O15<>"","Standards §6",IF(M15="HEADING ONLY","Derived from heading — PROVISIONAL",IF(M15="TEXT NOT IN REGISTRY","No text to derive from — PROVISIONAL","Derived from registered statement"))) | R15: =IF(OR(LEFT(G15,1)="A",L15="COUNTS",ISNUMBER(SEARCH("V1",P15)),ISNUMBER(SEARCH("V2",P15)),ISNUMBER(SEARCH("V5",P15))),"A — 100%","B — sample ≥ 30%")
A16: B5.1 | B16: Doc 1 | C16: RULED | D16: V7 — Document & design inspection | F16: Specification text against implementation description; provenance sections; objective card lines | G16: A — 100% | K16: =IFERROR(INDEX('Status Map'!$B$2:$B$12,MATCH(C16,'Status Map'!$A$2:$A$12,0)),"UNDEFINED") | L16: =IFERROR(INDEX('Status Map'!$C$2:$C$12,MATCH(C16,'Status Map'!$A$2:$A$12,0)),"UNDEFINED") | M16: HEADING ONLY | P16: =IF(O16<>"",O16,LEFT(D16,2)) | Q16: =IF(O16<>"","Standards §6",IF(M16="HEADING ONLY","Derived from heading — PROVISIONAL",IF(M16="TEXT NOT IN REGISTRY","No text to derive from — PROVISIONAL","Derived from registered statement"))) | R16: =IF(OR(LEFT(G16,1)="A",L16="COUNTS",ISNUMBER(SEARCH("V1",P16)),ISNUMBER(SEARCH("V2",P16)),ISNUMBER(SEARCH("V5",P16))),"A — 100%","B — sample ≥ 30%")
A17: B5.2 | B17: Doc 1 | C17: — | D17: V6 — Surface inspection | F17: DOM-bound substitution rule or harness receipt; fixed string verbatim; honest-gap variant rendered on null | G17: A — 100% | K17: =IFERROR(INDEX('Status Map'!$B$2:$B$12,MATCH(C17,'Status Map'!$A$2:$A$12,0)),"UNDEFINED") | L17: =IFERROR(INDEX('Status Map'!$C$2:$C$12,MATCH(C17,'Status Map'!$A$2:$A$12,0)),"UNDEFINED") | M17: HEADING ONLY | P17: =IF(O17<>"",O17,LEFT(D17,2)) | Q17: =IF(O17<>"","Standards §6",IF(M17="HEADING ONLY","Derived from heading — PROVISIONAL",IF(M17="TEXT NOT IN REGISTRY","No text to derive from — PROVISIONAL","Derived from registered statement"))) | R17: =IF(OR(LEFT(G17,1)="A",L17="COUNTS",ISNUMBER(SEARCH("V1",P17)),ISNUMBER(SEARCH("V2",P17)),ISNUMBER(SEARCH("V5",P17))),"A — 100%","B — sample ≥ 30%")
A18: B5.3 | B18: Doc 1 | C18: CANON | D18: V7 — Document & design inspection | F18: Specification text against implementation description; provenance sections; objective card lines | G18: A — 100% | K18: =IFERROR(INDEX('Status Map'!$B$2:$B$12,MATCH(C18,'Status Map'!$A$2:$A$12,0)),"UNDEFINED") | L18: =IFERROR(INDEX('Status Map'!$C$2:$C$12,MATCH(C18,'Status Map'!$A$2:$A$12,0)),"UNDEFINED") | M18: HEADING ONLY | P18: =IF(O18<>"",O18,LEFT(D18,2)) | Q18: =IF(O18<>"","Standards §6",IF(M18="HEADING ONLY","Derived from heading — PROVISIONAL",IF(M18="TEXT NOT IN REGISTRY","No text to derive from — PROVISIONAL","Derived from registered statement"))) | R18: =IF(OR(LEFT(G18,1)="A",L18="COUNTS",ISNUMBER(SEARCH("V1",P18)),ISNUMBER(SEARCH("V2",P18)),ISNUMBER(SEARCH("V5",P18))),"A — 100%","B — sample ≥ 30%")
A19: B5.4 | B19: Doc 1 | C19: CANON | D19: V3 — Record evidence | F19: Ledger rows inspected; hash-chain verifier receipt; refused operations present on identical terms | G19: A — 100% | K19: =IFERROR(INDEX('Status Map'!$B$2:$B$12,MATCH(C19,'Status Map'!$A$2:$A$12,0)),"UNDEFINED") | L19: =IFERROR(INDEX('Status Map'!$C$2:$C$12,MATCH(C19,'Status Map'!$A$2:$A$12,0)),"UNDEFINED") | M19: HEADING ONLY | P19: =IF(O19<>"",O19,LEFT(D19,2)) | Q19: =IF(O19<>"","Standards §6",IF(M19="HEADING ONLY","Derived from heading — PROVISIONAL",IF(M19="TEXT NOT IN REGISTRY","No text to derive from — PROVISIONAL","Derived from registered statement"))) | R19: =IF(OR(LEFT(G19,1)="A",L19="COUNTS",ISNUMBER(SEARCH("V1",P19)),ISNUMBER(SEARCH("V2",P19)),ISNUMBER(SEARCH("V5",P19))),"A — 100%","B — sample ≥ 30%")
A20: B5.5 | B20: Doc 1 | C20: RULED | D20: V7 — Document & design inspection | F20: Specification text against implementation description; provenance sections; objective card lines | G20: A — 100% | K20: =IFERROR(INDEX('Status Map'!$B$2:$B$12,MATCH(C20,'Status Map'!$A$2:$A$12,0)),"UNDEFINED") | L20: =IFERROR(INDEX('Status Map'!$C$2:$C$12,MATCH(C20,'Status Map'!$A$2:$A$12,0)),"UNDEFINED") | M20: HEADING ONLY | P20: =IF(O20<>"",O20,LEFT(D20,2)) | Q20: =IF(O20<>"","Standards §6",IF(M20="HEADING ONLY","Derived from heading — PROVISIONAL",IF(M20="TEXT NOT IN REGISTRY","No text to derive from — PROVISIONAL","Derived from registered statement"))) | R20: =IF(OR(LEFT(G20,1)="A",L20="COUNTS",ISNUMBER(SEARCH("V1",P20)),ISNUMBER(SEARCH("V2",P20)),ISNUMBER(SEARCH("V5",P20))),"A — 100%","B — sample ≥ 30%")
... A28: A5.2 | B28: Doc 15 | C28: — | D28: V7 — Document & design inspection | F28: Specification text against implementation description; provenance sections; objective card lines | G28: B — sample ≥ 30% | K28: =IFERROR(INDEX('Status Map'!$B$2:$B$12,MATCH(C28,'Status Map'!$A$2:$A$12,0)),"UNDEFINED") | L28: =IFERROR(INDEX('Status Map'!$C$2:$C$12,MATCH(C28,'Status Map'!$A$2:$A$12,0)),"UNDEFINED") | M28: HEADING ONLY | P28: =IF(O28<>"",O28,LEFT(D28,2)) | Q28: =IF(O28<>"","Standards §6",IF(M28="HEADING ONLY","Derived from heading — PROVISIONAL",IF(M28="TEXT NOT IN REGISTRY","No text to derive from — PROVISIONAL","Derived from registered statement"))) | R28: =IF(OR(LEFT(G28,1)="A",L28="COUNTS",ISNUMBER(SEARCH("V1",P28)),ISNUMBER(SEARCH("V2",P28)),ISNUMBER(SEARCH("V5",P28))),"A — 100%","B — sample ≥ 30%")
A29: A5.3 | B29: Doc 15 | C29: DETERMINED | D29: V7 — Document & design inspection | F29: Specification text against implementation description; provenance sections; objective card lines | G29: B — sample ≥ 30% | K29: =IFERROR(INDEX('Status Map'!$B$2:$B$12,MATCH(C29,'Status Map'!$A$2:$A$12,0)),"UNDEFINED") | L29: COUNTS | M29: HEADING ONLY | P29: =IF(O29<>"",O29,LEFT(D29,2)) | Q29: =IF(O29<>"","Standards §6",IF(M29="HEADING ONLY","Derived from heading — PROVISIONAL",IF(M29="TEXT NOT IN REGISTRY","No text to derive from — PROVISIONAL","Derived from registered statement"))) | R29: =IF(OR(LEFT(G29,1)="A",L29="COUNTS",ISNUMBER(SEARCH("V1",P29)),ISNUMBER(SEARCH("V2",P29)),ISNUMBER(SEARCH("V5",P29))),"A — 100%","B — sample ≥ 30%")
A30: A5.1 | B30: Doc 3 | C30: — | D30: V7 — Document & design inspection | F30: Specification text against implementation description; provenance sections; objective card lines | G30: A — 100% | K30: =IFERROR(INDEX('Status Map'!$B$2:$B$12,MATCH(C30,'Status Map'!$A$2:$A$12,0)),"UNDEFINED") | L30: =IFERROR(INDEX('Status Map'!$C$2:$C$12,MATCH(C30,'Status Map'!$A$2:$A$12,0)),"UNDEFINED") | M30: HEADING ONLY | P30: =IF(O30<>"",O30,LEFT(D30,2)) | Q30: =IF(O30<>"","Standards §6",IF(M30="HEADING ONLY","Derived from heading — PROVISIONAL",IF(M30="TEXT NOT IN REGISTRY","No text to derive from — PROVISIONAL","Derived from registered statement"))) | R30: =IF(OR(LEFT(G30,1)="A",L30="COUNTS",ISNUMBER(SEARCH("V1",P30)),ISNUMBER(SEARCH("V2",P30)),ISNUMBER(SEARCH("V5",P30))),"A — 100%","B — sample ≥ 30%")
A31: A5.10 | B31: Doc 3 | C31: — | D31: V7 — Document & design inspection | F31: Specification text against implementation description; provenance sections; objective card lines | G31: A — 100% | K31: =IFERROR(INDEX('Status Map'!$B$2:$B$12,MATCH(C31,'Status Map'!$A$2:$A$12,0)),"UNDEFINED") | L31: =IFERROR(INDEX('Status Map'!$C$2:$C$12,MATCH(C31,'Status Map'!$A$2:$A$12,0)),"UNDEFINED") | M31: HEADING ONLY | P31: =IF(O31<>"",O31,LEFT(D31,2)) | Q31: =IF(O31<>"","Standards §6",IF(M31="HEADING ONLY","Derived from heading — PROVISIONAL",IF(M31="TEXT NOT IN REGISTRY","No text to derive from — PROVISIONAL","Derived from registered statement"))) | R31: =IF(OR(LEFT(G31,1)="A",L31="COUNTS",ISNUMBER(SEARCH("V1",P31)),ISNUMBER(SEARCH("V2",P31)),ISNUMBER(SEARCH("V5",P31))),"A — 100%","B — sample ≥ 30%")
A32: A5.11 | B32: Doc 3 | C32: — | D32: V7 — Document & design inspection | F32: Specification text against implementation description; provenance sections; objective card lines | G32: A — 100% | K32: =IFERROR(INDEX('Status Map'!$B$2:$B$12,MATCH(C32,'Status Map'!$A$2:$A$12,0)),"UNDEFINED") | L32: =IFERROR(INDEX('Status Map'!$C$2:$C$12,MATCH(C32,'Status Map'!$A$2:$A$12,0)),"UNDEFINED") | M32: HEADING ONLY | P32: =IF(O32<>"",O32,LEFT(D32,2)) | Q32: =IF(O32<>"","Standards §6",IF(M32="HEADING ONLY","Derived from heading — PROVISIONAL",IF(M32="TEXT NOT IN REGISTRY","No text to derive from — PROVISIONAL","Derived from registered statement"))) | R32: =IF(OR(LEFT(G32,1)="A",L32="COUNTS",ISNUMBER(SEARCH("V1",P32)),ISNUMBER(SEARCH("V2",P32)),ISNUMBER(SEARCH("V5",P32))),"A — 100%","B — sample ≥ 30%")
A33: A5.12 | B33: Doc 3 | C33: — | D33: V7 — Document & design inspection | F33: Specification text against implementation description; provenance sections; objective card lines | G33: A — 100% | K33: =IFERROR(INDEX('Status Map'!$B$2:$B$12,MATCH(C33,'Status Map'!$A$2:$A$12,0)),"UNDEFINED") | L33: =IFERROR(INDEX('Status Map'!$C$2:$C$12,MATCH(C33,'Status Map'!$A$2:$A$12,0)),"UNDEFINED") | M33: HEADING ONLY | P33: =IF(O33<>"",O33,LEFT(D33,2)) | Q33: =IF(O33<>"","Standards §6",IF(M33="HEADING ONLY","Derived from heading — PROVISIONAL",IF(M33="TEXT NOT IN REGISTRY","No text to derive from — PROVISIONAL","Derived from registered statement"))) | R33: =IF(OR(LEFT(G33,1)="A",L33="COUNTS",ISNUMBER(SEARCH("V1",P33)),ISNUMBER(SEARCH("V2",P33)),ISNUMBER(SEARCH("V5",P33))),"A — 100%","B — sample ≥ 30%")
A34: A5.13 | B34: Doc 3 | C34: — | D34: V7 — Document & design inspection | F34: Specification text against implementation description; provenance sections; objective card lines | G34: A — 100% | K34: =IFERROR(INDEX('Status Map'!$B$2:$B$12,MATCH(C34,'Status Map'!$A$2:$A$12,0)),"UNDEFINED") | L34: =IFERROR(INDEX('Status Map'!$C$2:$C$12,MATCH(C34,'Status Map'!$A$2:$A$12,0)),"UNDEFINED") | M34: HEADING ONLY | P34: =IF(O34<>"",O34,LEFT(D34,2)) | Q34: =IF(O34<>"","Standards §6",IF(M34="HEADING ONLY","Derived from heading — PROVISIONAL",IF(M34="TEXT NOT IN REGISTRY","No text to derive from — PROVISIONAL","Derived from registered statement"))) | R34: =IF(OR(LEFT(G34,1)="A",L34="COUNTS",ISNUMBER(SEARCH("V1",P34)),ISNUMBER(SEARCH("V2",P34)),ISNUMBER(SEARCH("V5",P34))),"A — 100%","B — sample ≥ 30%")
A35: A5.14 | B35: Doc 3 | C35: — | D35: V7 — Document & design inspection | F35: Specification text against implementation description; provenance sections; objective card lines | G35: A — 100% | K35: =IFERROR(INDEX('Status Map'!$B$2:$B$12,MATCH(C35,'Status Map'!$A$2:$A$12,0)),"UNDEFINED") | L35: =IFERROR(INDEX('Status Map'!$C$2:$C$12,MATCH(C35,'Status Map'!$A$2:$A$12,0)),"UNDEFINED") | M35: HEADING ONLY | N35: C-6.4.7 | O35: V5 | P35: =IF(O35<>"",O35,LEFT(D35,2)) | Q35: =IF(O35<>"","Standards §6",IF(M35="HEADING ONLY","Derived from heading — PROVISIONAL",IF(M35="TEXT NOT IN REGISTRY","No text to derive from — PROVISIONAL","Derived from registered statement"))) | R35: =IF(OR(LEFT(G35,1)="A",L35="COUNTS",ISNUMBER(SEARCH("V1",P35)),ISNUMBER(SEARCH("V2",P35)),ISNUMBER(SEARCH("V5",P35))),"A — 100%","B — sample ≥ 30%")
A36: A5.2 | B36: Doc 3 | C36: — | D36: V7 — Document & design inspection | F36: Specification text against implementation description; provenance sections; objective card lines | G36: A — 100% | K36: =IFERROR(INDEX('Status Map'!$B$2:$B$12,MATCH(C36,'Status Map'!$A$2:$A$12,0)),"UNDEFINED") | L36: =IFERROR(INDEX('Status Map'!$C$2:$C$12,MATCH(C36,'Status Map'!$A$2:$A$12,0)),"UNDEFINED") | M36: HEADING ONLY | N36: C-6.4.3, C-6.4.4 | O36: V2 + V4 + V6 | P36: =IF(O36<>"",O36,LEFT(D36,2)) | Q36: =IF(O36<>"","Standards §6",IF(M36="HEADING ONLY","Derived from heading — PROVISIONAL",IF(M36="TEXT NOT IN REGISTRY","No text to derive from — PROVISIONAL","Derived from registered statement"))) | R36: =IF(OR(LEFT(G36,1)="A",L36="COUNTS",ISNUMBER(SEARCH("V1",P36)),ISNUMBER(SEARCH("V2",P36)),ISNUMBER(SEARCH("V5",P36))),"A — 100%","B — sample ≥ 30%")
A37: A5.3 | B37: Doc 3 | C37: — | D37: V4 — Governance-record evidence | F37: DECISIONS.md entry; ceremony record with tier, countersign, countdown, apply, re-verify; canon_ref present | G37: A — 100% | K37: =IFERROR(INDEX('Status Map'!$B$2:$B$12,MATCH(C37,'Status Map'!$A$2:$A$12,0)),"UNDEFINED") | L37: =IFERROR(INDEX('Status Map'!$C$2:$C$12,MATCH(C37,'Status Map'!$A$2:$A$12,0)),"UNDEFINED") | M37: HEADING ONLY | N37: C-6.4.5, C-6.4.7 | O37: V2 + V5 | P37: =IF(O37<>"",O37,LEFT(D37,2)) | Q37: =IF(O37<>"","Standards §6",IF(M37="HEADING ONLY","Derived from heading — PROVISIONAL",IF(M37="TEXT NOT IN REGISTRY","No text to derive from — PROVISIONAL","Derived from registered statement"))) | R37: =IF(OR(LEFT(G37,1)="A",L37="COUNTS",ISNUMBER(SEARCH("V1",P37)),ISNUMBER(SEARCH("V2",P37)),ISNUMBER(SEARCH("V5",P37))),"A — 100%","B — sample ≥ 30%")
A38: A5.4 | B38: Doc 3 | C38: — | D38: V7 — Document & design inspection | F38: Specification text against implementation description; provenance sections; objective card lines | G38: A — 100% | K38: =IFERROR(INDEX('Status Map'!$B$2:$B$12,MATCH(C38,'Status Map'!$A$2:$A$12,0)),"UNDEFINED") | L38: =IFERROR(INDEX('Status Map'!$C$2:$C$12,MATCH(C38,'Status Map'!$A$2:$A$12,0)),"UNDEFINED") | M38: HEADING ONLY | P38: =IF(O38<>"",O38,LEFT(D38,2)) | Q38: =IF(O38<>"","Standards §6",IF(M38="HEADING ONLY","Derived from heading — PROVISIONAL",IF(M38="TEXT NOT IN REGISTRY","No text to derive from — PROVISIONAL","Derived from registered statement"))) | R38: =IF(OR(LEFT(G38,1)="A",L38="COUNTS",ISNUMBER(SEARCH("V1",P38)),ISNUMBER(SEARCH("V2",P38)),ISNUMBER(SEARCH("V5",P38))),"A — 100%","B — sample ≥ 30%")
A39: A5.5 | B39: Doc 3 | C39: — | D39: V7 — Document & design inspection | F39: Specification text against implementation description; provenance sections; objective card lines | G39: A — 100% | K39: =IFERROR(INDEX('Status Map'!$B$2:$B$12,MATCH(C39,'Status Map'!$A$2:$A$12,0)),"UNDEFINED") | L39: =IFERROR(INDEX('Status Map'!$C$2:$C$12,MATCH(C39,'Status Map'!$A$2:$A$12,0)),"UNDEFINED") | M39: HEADING ONLY | P39: =IF(O39<>"",O39,LEFT(D39,2)) | Q39: =IF(O39<>"","Standards §6",IF(M39="HEADING ONLY","Derived from heading — PROVISIONAL",IF(M39="TEXT NOT IN REGISTRY","No text to derive from — PROVISIONAL","Derived from registered statement"))) | R39: =IF(OR(LEFT(G39,1)="A",L39="COUNTS",ISNUMBER(SEARCH("V1",P39)),ISNUMBER(SEARCH("V2",P39)),ISNUMBER(SEARCH("V5",P39))),"A — 100%","B — sample ≥ 30%")
A40: A5.6 | B40: Doc 3 | C40: — | D40: V7 — Document & design inspection | F40: Specification text against implementation description; provenance sections; objective card lines | G40: A — 100% | K40: =IFERROR(INDEX('Status Map'!$B$2:$B$12,MATCH(C40,'Status Map'!$A$2:$A$12,0)),"UNDEFINED") | L40: =IFERROR(INDEX('Status Map'!$C$2:$C$12,MATCH(C40,'Status Map'!$A$2:$A$12,0)),"UNDEFINED") | M40: HEADING ONLY | P40: =IF(O40<>"",O40,LEFT(D40,2)) | Q40: =IF(O40<>"","Standards §6",IF(M40="HEADING ONLY","Derived from heading — PROVISIONAL",IF(M40="TEXT NOT IN REGISTRY","No text to derive from — PROVISIONAL","Derived from registered statement"))) | R40: =IF(OR(LEFT(G40,1)="A",L40="COUNTS",ISNUMBER(SEARCH("V1",P40)),ISNUMBER(SEARCH("V2",P40)),ISNUMBER(SEARCH("V5",P40))),"A — 100%","B — sample ≥ 30%")
A41: A5.7 | B41: Doc 3 | C41: — | D41: V7 — Document & design inspection | F41: Specification text against implementation description; provenance sections; objective card lines | G41: A — 100% | K41: =IFERROR(INDEX('Status Map'!$B$2:$B$12,MATCH(C41,'Status Map'!$A$2:$A$12,0)),"UNDEFINED") | L41: =IFERROR(INDEX('Status Map'!$C$2:$C$12,MATCH(C41,'Status Map'!$A$2:$A$12,0)),"UNDEFINED") | M41: HEADING ONLY | P41: =IF(O41<>"",O41,LEFT(D41,2)) | Q41: =IF(O41<>"","Standards §6",IF(M41="HEADING ONLY","Derived from heading — PROVISIONAL",IF(M41="TEXT NOT IN REGISTRY","No text to derive from — PROVISIONAL","Derived from registered statement"))) | R41: =IF(OR(LEFT(G41,1)="A",L41="COUNTS",ISNUMBER(SEARCH("V1",P41)),ISNUMBER(SEARCH("V2",P41)),ISNUMBER(SEARCH("V5",P41))),"A — 100%","B — sample ≥ 30%")
A42: A5.8 | B42: Doc 3 | C42: — | D42: V7 — Document & design inspection | F42: Specification text against implementation description; provenance sections; objective card lines | G42: A — 100% | K42: =IFERROR(INDEX('Status Map'!$B$2:$B$12,MATCH(C42,'Status Map'!$A$2:$A$12,0)),"UNDEFINED") | L42: =IFERROR(INDEX('Status Map'!$C$2:$C$12,MATCH(C42,'Status Map'!$A$2:$A$12,0)),"UNDEFINED") | M42: HEADING ONLY | P42: =IF(O42<>"",O42,LEFT(D42,2)) | Q42: =IF(O42<>"","Standards §6",IF(M42="HEADING ONLY","Derived from heading — PROVISIONAL",IF(M42="TEXT NOT IN REGISTRY","No text to derive from — PROVISIONAL","Derived from registered statement"))) | R42: =IF(OR(LEFT(G42,1)="A",L42="COUNTS",ISNUMBER(SEARCH("V1",P42)),ISNUMBER(SEARCH("V2",P42)),ISNUMBER(SEARCH("V5",P42))),"A — 100%","B — sample ≥ 30%")
A43: A5.9 | B43: Doc 3 | C43: — | D43: V7 — Document & design inspection | F43: Specification text against implementation description; provenance sections; objective card lines | G43: A — 100% | K43: =IFERROR(INDEX('Status Map'!$B$2:$B$12,MATCH(C43,'Status Map'!$A$2:$A$12,0)),"UNDEFINED") | L43: =IFERROR(INDEX('Status Map'!$C$2:$C$12,MATCH(C43,'Status Map'!$A$2:$A$12,0)),"UNDEFINED") | M43: HEADING ONLY | P43: =IF(O43<>"",O43,LEFT(D43,2)) | Q43: =IF(O43<>"","Standards §6",IF(M43="HEADING ONLY","Derived from heading — PROVISIONAL",IF(M43="TEXT NOT IN REGISTRY","No text to derive from — PROVISIONAL","Derived from registered statement"))) | R43: =IF(OR(LEFT(G43,1)="A",L43="COUNTS",ISNUMBER(SEARCH("V1",P43)),ISNUMBER(SEARCH("V2",P43)),ISNUMBER(SEARCH("V5",P43))),"A — 100%","B — sample ≥ 30%")
A44: B5.1 | B44: Doc 3 | C44: CANON | D44: V7 — Document & design inspection | F44: Specification text against implementation description; provenance sections; objective card lines | G44: A — 100% | K44: =IFERROR(INDEX('Status Map'!$B$2:$B$12,MATCH(C44,'Status Map'!$A$2:$A$12,0)),"UNDEFINED") | L44: =IFERROR(INDEX('Status Map'!$C$2:$C$12,MATCH(C44,'Status Map'!$A$2:$A$12,0)),"UNDEFINED") | M44: HEADING ONLY | P44: =IF(O44<>"",O44,LEFT(D44,2)) | Q44: =IF(O44<>"","Standards §6",IF(M44="HEADING ONLY","Derived from heading — PROVISIONAL",IF(M44="TEXT NOT IN REGISTRY","No text to derive from — PROVISIONAL","Derived from registered statement"))) | R44: =IF(OR(LEFT(G44,1)="A",L44="COUNTS",ISNUMBER(SEARCH("V1",P44)),ISNUMBER(SEARCH("V2",P44)),ISNUMBER(SEARCH("V5",P44))),"A — 100%","B — sample ≥ 30%")
A45: B5.2 | B45: Doc 3 | C45: CANON | D45: V1 — Test evidence | F45: Golden-input, byte-identical output; RED-first test ID; ratchet manifest entry | G45: A — 100% | K45: =IFERROR(INDEX('Status Map'!$B$2:$B$12,MATCH(C45,'Status Map'!$A$2:$A$12,0)),"UNDEFINED") | L45: =IFERROR(INDEX('Status Map'!$C$2:$C$12,MATCH(C45,'Status Map'!$A$2:$A$12,0)),"UNDEFINED") | M45: HEADING ONLY | P45: =IF(O45<>"",O45,LEFT(D45,2)) | Q45: =IF(O45<>"","Standards §6",IF(M45="HEADING ONLY","Derived from heading — PROVISIONAL",IF(M45="TEXT NOT IN REGISTRY","No text to derive from — PROVISIONAL","Derived from registered statement"))) | R45: =IF(OR(LEFT(G45,1)="A",L45="COUNTS",ISNUMBER(SEARCH("V1",P45)),ISNUMBER(SEARCH("V2",P45)),ISNUMBER(SEARCH("V5",P45))),"A — 100%","B — sample ≥ 30%")
A46: B5.3 | B46: Doc 3 | C46: CANON | D46: V7 — Document & design inspection | F46: Specification text against implementation description; provenance sections; objective card lines | G46: A — 100% | K46: =IFERROR(INDEX('Status Map'!$B$2:$B$12,MATCH(C46,'Status Map'!$A$2:$A$12,0)),"UNDEFINED") | L46: =IFERROR(INDEX('Status Map'!$C$2:$C$12,MATCH(C46,'Status Map'!$A$2:$A$12,0)),"UNDEFINED") | M46: HEADING ONLY | P46: =IF(O46<>"",O46,LEFT(D46,2)) | Q46: =IF(O46<>"","Standards §6",IF(M46="HEADING ONLY","Derived from heading — PROVISIONAL",IF(M46="TEXT NOT IN REGISTRY","No text to derive from — PROVISIONAL","Derived from registered statement"))) | R46: =IF(OR(LEFT(G46,1)="A",L46="COUNTS",ISNUMBER(SEARCH("V1",P46)),ISNUMBER(SEARCH("V2",P46)),ISNUMBER(SEARCH("V5",P46))),"A — 100%","B — sample ≥ 30%")
A47: B5.4 | B47: Doc 3 | C47: CANON | D47: V3 — Record evidence | F47: Ledger rows inspected; hash-chain verifier receipt; refused operations present on identical terms | G47: A — 100% | K47: =IFERROR(INDEX('Status Map'!$B$2:$B$12,MATCH(C47,'Status Map'!$A$2:$A$12,0)),"UNDEFINED") | L47: =IFERROR(INDEX('Status Map'!$C$2:$C$12,MATCH(C47,'Status Map'!$A$2:$A$12,0)),"UNDEFINED") | M47: HEADING ONLY | P47: =IF(O47<>"",O47,LEFT(D47,2)) | Q47: =IF(O47<>"","Standards §6",IF(M47="HEADING ONLY","Derived from heading — PROVISIONAL",IF(M47="TEXT NOT IN REGISTRY","No text to derive from — PROVISIONAL","Derived from registered statement"))) | R47: =IF(OR(LEFT(G47,1)="A",L47="COUNTS",ISNUMBER(SEARCH("V1",P47)),ISNUMBER(SEARCH("V2",P47)),ISNUMBER(SEARCH("V5",P47))),"A — 100%","B — sample ≥ 30%")
A48: B5.5 | B48: Doc 3 | C48: CANON | D48: V7 — Document & design inspection | F48: Specification text against implementation description; provenance sections; objective card lines | G48: A — 100% | K48: =IFERROR(INDEX('Status Map'!$B$2:$B$12,MATCH(C48,'Status Map'!$A$2:$A$12,0)),"UNDEFINED") | L48: =IFERROR(INDEX('Status Map'!$C$2:$C$12,MATCH(C48,'Status Map'!$A$2:$A$12,0)),"UNDEFINED") | M48: HEADING ONLY | P48: =IF(O48<>"",O48,LEFT(D48,2)) | Q48: =IF(O48<>"","Standards §6",IF(M48="HEADING ONLY","Derived from heading — PROVISIONAL",IF(M48="TEXT NOT IN REGISTRY","No text to derive from — PROVISIONAL","Derived from registered statement"))) | R48: =IF(OR(LEFT(G48,1)="A",L48="COUNTS",ISNUMBER(SEARCH("V1",P48)),ISNUMBER(SEARCH("V2",P48)),ISNUMBER(SEARCH("V5",P48))),"A — 100%","B — sample ≥ 30%")
A49: B5.1 | B49: Doc 4 | C49: CANON | D49: V7 — Document & design inspection | F49: Specification text against implementation description; provenance sections; objective card lines | G49: A — 100% | K49: =IFERROR(INDEX('Status Map'!$B$2:$B$12,MATCH(C49,'Status Map'!$A$2:$A$12,0)),"UNDEFINED") | L49: =IFERROR(INDEX('Status Map'!$C$2:$C$12,MATCH(C49,'Status Map'!$A$2:$A$12,0)),"UNDEFINED") | M49: HEADING ONLY | P49: =IF(O49<>"",O49,LEFT(D49,2)) | Q49: =IF(O49<>"","Standards §6",IF(M49="HEADING ONLY","Derived from heading — PROVISIONAL",IF(M49="TEXT NOT IN REGISTRY","No text to derive from — PROVISIONAL","Derived from registered statement"))) | R49: =IF(OR(LEFT(G49,1)="A",L49="COUNTS",ISNUMBER(SEARCH("V1",P49)),ISNUMBER(SEARCH("V2",P49)),ISNUMBER(SEARCH("V5",P49))),"A — 100%","B — sample ≥ 30%")
... A206: A20.11 | B206: Doc 20 | C206: CANON | D206: V7 — Document & design inspection | F206: Specification text against implementation description; provenance sections; objective card lines | G206: B — sample ≥ 30% | K206: =IFERROR(INDEX('Status Map'!$B$2:$B$12,MATCH(C206,'Status Map'!$A$2:$A$12,0)),"UNDEFINED") | L206: =IFERROR(INDEX('Status Map'!$C$2:$C$12,MATCH(C206,'Status Map'!$A$2:$A$12,0)),"UNDEFINED") | M206: HEADING ONLY | P206: =IF(O206<>"",O206,LEFT(D206,2)) | Q206: =IF(O206<>"","Standards §6",IF(M206="HEADING ONLY","Derived from heading — PROVISIONAL",IF(M206="TEXT NOT IN REGISTRY","No text to derive from — PROVISIONAL","Derived from registered statement"))) | R206: =IF(OR(LEFT(G206,1)="A",L206="COUNTS",ISNUMBER(SEARCH("V1",P206)),ISNUMBER(SEARCH("V2",P206)),ISNUMBER(SEARCH("V5",P206))),"A — 100%","B — sample ≥ 30%")
A207: A20.12 | B207: Doc 20 | C207: PROPOSED | D207: V1 — Test evidence | E207: V2 | F207: Golden-input, byte-identical output; RED-first test ID; ratchet manifest entry | G207: A — 100% | K207: =IFERROR(INDEX('Status Map'!$B$2:$B$12,MATCH(C207,'Status Map'!$A$2:$A$12,0)),"UNDEFINED") | L207: =IFERROR(INDEX('Status Map'!$C$2:$C$12,MATCH(C207,'Status Map'!$A$2:$A$12,0)),"UNDEFINED") | M207: HEADING ONLY | P207: =IF(O207<>"",O207,LEFT(D207,2)) | Q207: =IF(O207<>"","Standards §6",IF(M207="HEADING ONLY","Derived from heading — PROVISIONAL",IF(M207="TEXT NOT IN REGISTRY","No text to derive from — PROVISIONAL","Derived from registered statement"))) | R207: =IF(OR(LEFT(G207,1)="A",L207="COUNTS",ISNUMBER(SEARCH("V1",P207)),ISNUMBER(SEARCH("V2",P207)),ISNUMBER(SEARCH("V5",P207))),"A — 100%","B — sample ≥ 30%")
A208: A20.13 | B208: Doc 20 | C208: PROPOSED | D208: V7 — Document & design inspection | F208: Specification text against implementation description; provenance sections; objective card lines | G208: B — sample ≥ 30% | K208: =IFERROR(INDEX('Status Map'!$B$2:$B$12,MATCH(C208,'Status Map'!$A$2:$A$12,0)),"UNDEFINED") | L208: =IFERROR(INDEX('Status Map'!$C$2:$C$12,MATCH(C208,'Status Map'!$A$2:$A$12,0)),"UNDEFINED") | M208: HEADING ONLY | P208: =IF(O208<>"",O208,LEFT(D208,2)) | Q208: =IF(O208<>"","Standards §6",IF(M208="HEADING ONLY","Derived from heading — PROVISIONAL",IF(M208="TEXT NOT IN REGISTRY","No text to derive from — PROVISIONAL","Derived from registered statement"))) | R208: =IF(OR(LEFT(G208,1)="A",L208="COUNTS",ISNUMBER(SEARCH("V1",P208)),ISNUMBER(SEARCH("V2",P208)),ISNUMBER(SEARCH("V5",P208))),"A — 100%","B — sample ≥ 30%")
A209: A20.14 | B209: Doc 20 | C209: PROPOSED | D209: V6 — Surface inspection | F209: DOM-bound substitution rule or harness receipt; fixed string verbatim; honest-gap variant rendered on null | G209: B — sample ≥ 30% | K209: =IFERROR(INDEX('Status Map'!$B$2:$B$12,MATCH(C209,'Status Map'!$A$2:$A$12,0)),"UNDEFINED") | L209: =IFERROR(INDEX('Status Map'!$C$2:$C$12,MATCH(C209,'Status Map'!$A$2:$A$12,0)),"UNDEFINED") | M209: HEADING ONLY | P209: =IF(O209<>"",O209,LEFT(D209,2)) | Q209: =IF(O209<>"","Standards §6",IF(M209="HEADING ONLY","Derived from heading — PROVISIONAL",IF(M209="TEXT NOT IN REGISTRY","No text to derive from — PROVISIONAL","Derived from registered statement"))) | R209: =IF(OR(LEFT(G209,1)="A",L209="COUNTS",ISNUMBER(SEARCH("V1",P209)),ISNUMBER(SEARCH("V2",P209)),ISNUMBER(SEARCH("V5",P209))),"A — 100%","B — sample ≥ 30%")
A210: A20.2 | B210: Doc 20 | C210: CANON | D210: V7 — Document & design inspection | F210: Specification text against implementation description; provenance sections; objective card lines | G210: B — sample ≥ 30% | K210: =IFERROR(INDEX('Status Map'!$B$2:$B$12,MATCH(C210,'Status Map'!$A$2:$A$12,0)),"UNDEFINED") | L210: =IFERROR(INDEX('Status Map'!$C$2:$C$12,MATCH(C210,'Status Map'!$A$2:$A$12,0)),"UNDEFINED") | M210: HEADING ONLY | P210: =IF(O210<>"",O210,LEFT(D210,2)) | Q210: =IF(O210<>"","Standards §6",IF(M210="HEADING ONLY","Derived from heading — PROVISIONAL",IF(M210="TEXT NOT IN REGISTRY","No text to derive from — PROVISIONAL","Derived from registered statement"))) | R210: =IF(OR(LEFT(G210,1)="A",L210="COUNTS",ISNUMBER(SEARCH("V1",P210)),ISNUMBER(SEARCH("V2",P210)),ISNUMBER(SEARCH("V5",P210))),"A — 100%","B — sample ≥ 30%")
A211: A20.3 | B211: Doc 20 | C211: PROPOSED | D211: V7 — Document & design inspection | F211: Specification text against implementation description; provenance sections; objective card lines | G211: B — sample ≥ 30% | K211: =IFERROR(INDEX('Status Map'!$B$2:$B$12,MATCH(C211,'Status Map'!$A$2:$A$12,0)),"UNDEFINED") | L211: =IFERROR(INDEX('Status Map'!$C$2:$C$12,MATCH(C211,'Status Map'!$A$2:$A$12,0)),"UNDEFINED") | M211: HEADING ONLY | P211: =IF(O211<>"",O211,LEFT(D211,2)) | Q211: =IF(O211<>"","Standards §6",IF(M211="HEADING ONLY","Derived from heading — PROVISIONAL",IF(M211="TEXT NOT IN REGISTRY","No text to derive from — PROVISIONAL","Derived from registered statement"))) | R211: =IF(OR(LEFT(G211,1)="A",L211="COUNTS",ISNUMBER(SEARCH("V1",P211)),ISNUMBER(SEARCH("V2",P211)),ISNUMBER(SEARCH("V5",P211))),"A — 100%","B — sample ≥ 30%")
A212: A20.4 | B212: Doc 20 | C212: PROPOSED | D212: V7 — Document & design inspection | F212: Specification text against implementation description; provenance sections; objective card lines | G212: B — sample ≥ 30% | K212: =IFERROR(INDEX('Status Map'!$B$2:$B$12,MATCH(C212,'Status Map'!$A$2:$A$12,0)),"UNDEFINED") | L212: =IFERROR(INDEX('Status Map'!$C$2:$C$12,MATCH(C212,'Status Map'!$A$2:$A$12,0)),"UNDEFINED") | M212: HEADING ONLY | P212: =IF(O212<>"",O212,LEFT(D212,2)) | Q212: =IF(O212<>"","Standards §6",IF(M212="HEADING ONLY","Derived from heading — PROVISIONAL",IF(M212="TEXT NOT IN REGISTRY","No text to derive from — PROVISIONAL","Derived from registered statement"))) | R212: =IF(OR(LEFT(G212,1)="A",L212="COUNTS",ISNUMBER(SEARCH("V1",P212)),ISNUMBER(SEARCH("V2",P212)),ISNUMBER(SEARCH("V5",P212))),"A — 100%","B — sample ≥ 30%")
A213: A20.5 | B213: Doc 20 | C213: PROPOSED | D213: V7 — Document & design inspection | F213: Specification text against implementation description; provenance sections; objective card lines | G213: B — sample ≥ 30% | K213: =IFERROR(INDEX('Status Map'!$B$2:$B$12,MATCH(C213,'Status Map'!$A$2:$A$12,0)),"UNDEFINED") | L213: =IFERROR(INDEX('Status Map'!$C$2:$C$12,MATCH(C213,'Status Map'!$A$2:$A$12,0)),"UNDEFINED") | M213: HEADING ONLY | P213: =IF(O213<>"",O213,LEFT(D213,2)) | Q213: =IF(O213<>"","Standards §6",IF(M213="HEADING ONLY","Derived from heading — PROVISIONAL",IF(M213="TEXT NOT IN REGISTRY","No text to derive from — PROVISIONAL","Derived from registered statement"))) | R213: =IF(OR(LEFT(G213,1)="A",L213="COUNTS",ISNUMBER(SEARCH("V1",P213)),ISNUMBER(SEARCH("V2",P213)),ISNUMBER(SEARCH("V5",P213))),"A — 100%","B — sample ≥ 30%")
A214: A20.6 | B214: Doc 20 | C214: PROPOSED | D214: V7 — Document & design inspection | F214: Specification text against implementation description; provenance sections; objective card lines | G214: B — sample ≥ 30% | K214: =IFERROR(INDEX('Status Map'!$B$2:$B$12,MATCH(C214,'Status Map'!$A$2:$A$12,0)),"UNDEFINED") | L214: =IFERROR(INDEX('Status Map'!$C$2:$C$12,MATCH(C214,'Status Map'!$A$2:$A$12,0)),"UNDEFINED") | M214: HEADING ONLY | P214: =IF(O214<>"",O214,LEFT(D214,2)) | Q214: =IF(O214<>"","Standards §6",IF(M214="HEADING ONLY","Derived from heading — PROVISIONAL",IF(M214="TEXT NOT IN REGISTRY","No text to derive from — PROVISIONAL","Derived from registered statement"))) | R214: =IF(OR(LEFT(G214,1)="A",L214="COUNTS",ISNUMBER(SEARCH("V1",P214)),ISNUMBER(SEARCH("V2",P214)),ISNUMBER(SEARCH("V5",P214))),"A — 100%","B — sample ≥ 30%")
A215: A20.7 | B215: Doc 20 | C215: PROPOSED | D215: V7 — Document & design inspection | F215: Specification text against implementation description; provenance sections; objective card lines | G215: B — sample ≥ 30% | K215: =IFERROR(INDEX('Status Map'!$B$2:$B$12,MATCH(C215,'Status Map'!$A$2:$A$12,0)),"UNDEFINED") | L215: =IFERROR(INDEX('Status Map'!$C$2:$C$12,MATCH(C215,'Status Map'!$A$2:$A$12,0)),"UNDEFINED") | M215: HEADING ONLY | P215: =IF(O215<>"",O215,LEFT(D215,2)) | Q215: =IF(O215<>"","Standards §6",IF(M215="HEADING ONLY","Derived from heading — PROVISIONAL",IF(M215="TEXT NOT IN REGISTRY","No text to derive from — PROVISIONAL","Derived from registered statement"))) | R215: =IF(OR(LEFT(G215,1)="A",L215="COUNTS",ISNUMBER(SEARCH("V1",P215)),ISNUMBER(SEARCH("V2",P215)),ISNUMBER(SEARCH("V5",P215))),"A — 100%","B — sample ≥ 30%")
A216: A20.8 | B216: Doc 20 | C216: PROPOSED | D216: V7 — Document & design inspection | F216: Specification text against implementation description; provenance sections; objective card lines | G216: B — sample ≥ 30% | K216: =IFERROR(INDEX('Status Map'!$B$2:$B$12,MATCH(C216,'Status Map'!$A$2:$A$12,0)),"UNDEFINED") | L216: =IFERROR(INDEX('Status Map'!$C$2:$C$12,MATCH(C216,'Status Map'!$A$2:$A$12,0)),"UNDEFINED") | M216: HEADING ONLY | P216: =IF(O216<>"",O216,LEFT(D216,2)) | Q216: =IF(O216<>"","Standards §6",IF(M216="HEADING ONLY","Derived from heading — PROVISIONAL",IF(M216="TEXT NOT IN REGISTRY","No text to derive from — PROVISIONAL","Derived from registered statement"))) | R216: =IF(OR(LEFT(G216,1)="A",L216="COUNTS",ISNUMBER(SEARCH("V1",P216)),ISNUMBER(SEARCH("V2",P216)),ISNUMBER(SEARCH("V5",P216))),"A — 100%","B — sample ≥ 30%")
A217: A20.9 | B217: Doc 20 | C217: PROPOSED | D217: V7 — Document & design inspection | F217: Specification text against implementation description; provenance sections; objective card lines | G217: B — sample ≥ 30% | K217: =IFERROR(INDEX('Status Map'!$B$2:$B$12,MATCH(C217,'Status Map'!$A$2:$A$12,0)),"UNDEFINED") | L217: =IFERROR(INDEX('Status Map'!$C$2:$C$12,MATCH(C217,'Status Map'!$A$2:$A$12,0)),"UNDEFINED") | M217: HEADING ONLY | P217: =IF(O217<>"",O217,LEFT(D217,2)) | Q217: =IF(O217<>"","Standards §6",IF(M217="HEADING ONLY","Derived from heading — PROVISIONAL",IF(M217="TEXT NOT IN REGISTRY","No text to derive from — PROVISIONAL","Derived from registered statement"))) | R217: =IF(OR(LEFT(G217,1)="A",L217="COUNTS",ISNUMBER(SEARCH("V1",P217)),ISNUMBER(SEARCH("V2",P217)),ISNUMBER(SEARCH("V5",P217))),"A — 100%","B — sample ≥ 30%")
A218: LT-1 | B218: SV extension | C218: PROPOSED | D218: V7 — Document & design inspection | F218: Specification text against implementation description; provenance sections; objective card lines | G218: B — sample ≥ 30% | K218: =IFERROR(INDEX('Status Map'!$B$2:$B$12,MATCH(C218,'Status Map'!$A$2:$A$12,0)),"UNDEFINED") | L218: =IFERROR(INDEX('Status Map'!$C$2:$C$12,MATCH(C218,'Status Map'!$A$2:$A$12,0)),"UNDEFINED") | M218: STATEMENT AS REGISTERED | P218: =IF(O218<>"",O218,LEFT(D218,2)) | Q218: =IF(O218<>"","Standards §6",IF(M218="HEADING ONLY","Derived from heading — PROVISIONAL",IF(M218="TEXT NOT IN REGISTRY","No text to derive from — PROVISIONAL","Derived from registered statement"))) | R218: =IF(OR(LEFT(G218,1)="A",L218="COUNTS",ISNUMBER(SEARCH("V1",P218)),ISNUMBER(SEARCH("V2",P218)),ISNUMBER(SEARCH("V5",P218))),"A — 100%","B — sample ≥ 30%")
A219: LT-2 | B219: SV extension | C219: OPEN | D219: V7 — Document & design inspection | F219: Specification text against implementation description; provenance sections; objective card lines | G219: B — sample ≥ 30% | K219: =IFERROR(INDEX('Status Map'!$B$2:$B$12,MATCH(C219,'Status Map'!$A$2:$A$12,0)),"UNDEFINED") | L219: =IFERROR(INDEX('Status Map'!$C$2:$C$12,MATCH(C219,'Status Map'!$A$2:$A$12,0)),"UNDEFINED") | M219: STATEMENT AS REGISTERED | P219: =IF(O219<>"",O219,LEFT(D219,2)) | Q219: =IF(O219<>"","Standards §6",IF(M219="HEADING ONLY","Derived from heading — PROVISIONAL",IF(M219="TEXT NOT IN REGISTRY","No text to derive from — PROVISIONAL","Derived from registered statement"))) | R219: =IF(OR(LEFT(G219,1)="A",L219="COUNTS",ISNUMBER(SEARCH("V1",P219)),ISNUMBER(SEARCH("V2",P219)),ISNUMBER(SEARCH("V5",P219))),"A — 100%","B — sample ≥ 30%")
... A254: EP-5 | B254: Doc 19 | C254: PROPOSED | D254: V7 — Document & design inspection | F254: Specification text against implementation description; provenance sections; objective card lines | G254: B — sample ≥ 30% | K254: =IFERROR(INDEX('Status Map'!$B$2:$B$12,MATCH(C254,'Status Map'!$A$2:$A$12,0)),"UNDEFINED") | L254: =IFERROR(INDEX('Status Map'!$C$2:$C$12,MATCH(C254,'Status Map'!$A$2:$A$12,0)),"UNDEFINED") | M254: HEADING ONLY | P254: =IF(O254<>"",O254,LEFT(D254,2)) | Q254: =IF(O254<>"","Standards §6",IF(M254="HEADING ONLY","Derived from heading — PROVISIONAL",IF(M254="TEXT NOT IN REGISTRY","No text to derive from — PROVISIONAL","Derived from registered statement"))) | R254: =IF(OR(LEFT(G254,1)="A",L254="COUNTS",ISNUMBER(SEARCH("V1",P254)),ISNUMBER(SEARCH("V2",P254)),ISNUMBER(SEARCH("V5",P254))),"A — 100%","B — sample ≥ 30%")
A255: DR-R1 | B255: Deck Engine spec | C255: OWNER-DIRECTED → CANON (R3/R5/R7/R9 strikeable) | D255: V6 — Surface inspection | F255: DOM-bound substitution rule or harness receipt; fixed string verbatim; honest-gap variant rendered on null | G255: B — sample ≥ 30% | K255: =IFERROR(INDEX('Status Map'!$B$2:$B$12,MATCH(C255,'Status Map'!$A$2:$A$12,0)),"UNDEFINED") | L255: COUNTS | M255: FIRST SENTENCE | P255: =IF(O255<>"",O255,LEFT(D255,2)) | Q255: =IF(O255<>"","Standards §6",IF(M255="HEADING ONLY","Derived from heading — PROVISIONAL",IF(M255="TEXT NOT IN REGISTRY","No text to derive from — PROVISIONAL","Derived from registered statement"))) | R255: =IF(OR(LEFT(G255,1)="A",L255="COUNTS",ISNUMBER(SEARCH("V1",P255)),ISNUMBER(SEARCH("V2",P255)),ISNUMBER(SEARCH("V5",P255))),"A — 100%","B — sample ≥ 30%")
A256: DR-R10 | B256: Deck Engine spec | C256: OPEN | D256: V7 — Document & design inspection | F256: Specification text against implementation description; provenance sections; objective card lines | G256: B — sample ≥ 30% | K256: =IFERROR(INDEX('Status Map'!$B$2:$B$12,MATCH(C256,'Status Map'!$A$2:$A$12,0)),"UNDEFINED") | L256: =IFERROR(INDEX('Status Map'!$C$2:$C$12,MATCH(C256,'Status Map'!$A$2:$A$12,0)),"UNDEFINED") | M256: FIRST SENTENCE | P256: =IF(O256<>"",O256,LEFT(D256,2)) | Q256: =IF(O256<>"","Standards §6",IF(M256="HEADING ONLY","Derived from heading — PROVISIONAL",IF(M256="TEXT NOT IN REGISTRY","No text to derive from — PROVISIONAL","Derived from registered statement"))) | R256: =IF(OR(LEFT(G256,1)="A",L256="COUNTS",ISNUMBER(SEARCH("V1",P256)),ISNUMBER(SEARCH("V2",P256)),ISNUMBER(SEARCH("V5",P256))),"A — 100%","B — sample ≥ 30%")
A257: DR-R11 | B257: Deck Engine spec | C257: OWNER-DIRECTED → CANON (R3/R5/R7/R9 strikeable) | D257: V1 — Test evidence | F257: Golden-input, byte-identical output; RED-first test ID; ratchet manifest entry | G257: A — 100% | K257: =IFERROR(INDEX('Status Map'!$B$2:$B$12,MATCH(C257,'Status Map'!$A$2:$A$12,0)),"UNDEFINED") | L257: COUNTS | M257: FIRST SENTENCE | P257: =IF(O257<>"",O257,LEFT(D257,2)) | Q257: =IF(O257<>"","Standards §6",IF(M257="HEADING ONLY","Derived from heading — PROVISIONAL",IF(M257="TEXT NOT IN REGISTRY","No text to derive from — PROVISIONAL","Derived from registered statement"))) | R257: =IF(OR(LEFT(G257,1)="A",L257="COUNTS",ISNUMBER(SEARCH("V1",P257)),ISNUMBER(SEARCH("V2",P257)),ISNUMBER(SEARCH("V5",P257))),"A — 100%","B — sample ≥ 30%")
A258: DR-R12 | B258: Deck Engine spec | C258: OWNER-DIRECTED → CANON (R3/R5/R7/R9 strikeable) | D258: V3 — Record evidence | E258: V6 | F258: Ledger rows inspected; hash-chain verifier receipt; refused operations present on identical terms | G258: B — sample ≥ 30% | K258: =IFERROR(INDEX('Status Map'!$B$2:$B$12,MATCH(C258,'Status Map'!$A$2:$A$12,0)),"UNDEFINED") | L258: COUNTS | M258: FIRST SENTENCE | P258: =IF(O258<>"",O258,LEFT(D258,2)) | Q258: =IF(O258<>"","Standards §6",IF(M258="HEADING ONLY","Derived from heading — PROVISIONAL",IF(M258="TEXT NOT IN REGISTRY","No text to derive from — PROVISIONAL","Derived from registered statement"))) | R258: =IF(OR(LEFT(G258,1)="A",L258="COUNTS",ISNUMBER(SEARCH("V1",P258)),ISNUMBER(SEARCH("V2",P258)),ISNUMBER(SEARCH("V5",P258))),"A — 100%","B — sample ≥ 30%")
A259: DR-R13 | B259: Deck Engine spec | C259: OPEN | D259: V7 — Document & design inspection | F259: Specification text against implementation description; provenance sections; objective card lines | G259: B — sample ≥ 30% | K259: =IFERROR(INDEX('Status Map'!$B$2:$B$12,MATCH(C259,'Status Map'!$A$2:$A$12,0)),"UNDEFINED") | L259: =IFERROR(INDEX('Status Map'!$C$2:$C$12,MATCH(C259,'Status Map'!$A$2:$A$12,0)),"UNDEFINED") | M259: FIRST SENTENCE | P259: =IF(O259<>"",O259,LEFT(D259,2)) | Q259: =IF(O259<>"","Standards §6",IF(M259="HEADING ONLY","Derived from heading — PROVISIONAL",IF(M259="TEXT NOT IN REGISTRY","No text to derive from — PROVISIONAL","Derived from registered statement"))) | R259: =IF(OR(LEFT(G259,1)="A",L259="COUNTS",ISNUMBER(SEARCH("V1",P259)),ISNUMBER(SEARCH("V2",P259)),ISNUMBER(SEARCH("V5",P259))),"A — 100%","B — sample ≥ 30%")
A260: DR-R14 | B260: Deck Engine spec | C260: OWNER-DIRECTED → CANON (R3/R5/R7/R9 strikeable) | D260: V7 — Document & design inspection | F260: Specification text against implementation description; provenance sections; objective card lines | G260: B — sample ≥ 30% | K260: =IFERROR(INDEX('Status Map'!$B$2:$B$12,MATCH(C260,'Status Map'!$A$2:$A$12,0)),"UNDEFINED") | L260: COUNTS | M260: FIRST SENTENCE | P260: =IF(O260<>"",O260,LEFT(D260,2)) | Q260: =IF(O260<>"","Standards §6",IF(M260="HEADING ONLY","Derived from heading — PROVISIONAL",IF(M260="TEXT NOT IN REGISTRY","No text to derive from — PROVISIONAL","Derived from registered statement"))) | R260: =IF(OR(LEFT(G260,1)="A",L260="COUNTS",ISNUMBER(SEARCH("V1",P260)),ISNUMBER(SEARCH("V2",P260)),ISNUMBER(SEARCH("V5",P260))),"A — 100%","B — sample ≥ 30%")
A261: DR-R2 | B261: Deck Engine spec | C261: OWNER-DIRECTED → CANON (R3/R5/R7/R9 strikeable) | D261: V1 — Test evidence | F261: Golden-input, byte-identical output; RED-first test ID; ratchet manifest entry | G261: A — 100% | K261: =IFERROR(INDEX('Status Map'!$B$2:$B$12,MATCH(C261,'Status Map'!$A$2:$A$12,0)),"UNDEFINED") | L261: COUNTS | M261: FIRST SENTENCE | P261: =IF(O261<>"",O261,LEFT(D261,2)) | Q261: =IF(O261<>"","Standards §6",IF(M261="HEADING ONLY","Derived from heading — PROVISIONAL",IF(M261="TEXT NOT IN REGISTRY","No text to derive from — PROVISIONAL","Derived from registered statement"))) | R261: =IF(OR(LEFT(G261,1)="A",L261="COUNTS",ISNUMBER(SEARCH("V1",P261)),ISNUMBER(SEARCH("V2",P261)),ISNUMBER(SEARCH("V5",P261))),"A — 100%","B — sample ≥ 30%")
A262: DR-R3 | B262: Deck Engine spec | C262: OWNER-DIRECTED → CANON (R3/R5/R7/R9 strikeable) | D262: V6 — Surface inspection | F262: DOM-bound substitution rule or harness receipt; fixed string verbatim; honest-gap variant rendered on null | G262: B — sample ≥ 30% | K262: =IFERROR(INDEX('Status Map'!$B$2:$B$12,MATCH(C262,'Status Map'!$A$2:$A$12,0)),"UNDEFINED") | L262: COUNTS | M262: FIRST SENTENCE | P262: =IF(O262<>"",O262,LEFT(D262,2)) | Q262: =IF(O262<>"","Standards §6",IF(M262="HEADING ONLY","Derived from heading — PROVISIONAL",IF(M262="TEXT NOT IN REGISTRY","No text to derive from — PROVISIONAL","Derived from registered statement"))) | R262: =IF(OR(LEFT(G262,1)="A",L262="COUNTS",ISNUMBER(SEARCH("V1",P262)),ISNUMBER(SEARCH("V2",P262)),ISNUMBER(SEARCH("V5",P262))),"A — 100%","B — sample ≥ 30%")
A263: DR-R4 | B263: Deck Engine spec | C263: OWNER-DIRECTED → CANON (R3/R5/R7/R9 strikeable) | D263: V7 — Document & design inspection | F263: Specification text against implementation description; provenance sections; objective card lines | G263: B — sample ≥ 30% | K263: =IFERROR(INDEX('Status Map'!$B$2:$B$12,MATCH(C263,'Status Map'!$A$2:$A$12,0)),"UNDEFINED") | L263: COUNTS | M263: FIRST SENTENCE | P263: =IF(O263<>"",O263,LEFT(D263,2)) | Q263: =IF(O263<>"","Standards §6",IF(M263="HEADING ONLY","Derived from heading — PROVISIONAL",IF(M263="TEXT NOT IN REGISTRY","No text to derive from — PROVISIONAL","Derived from registered statement"))) | R263: =IF(OR(LEFT(G263,1)="A",L263="COUNTS",ISNUMBER(SEARCH("V1",P263)),ISNUMBER(SEARCH("V2",P263)),ISNUMBER(SEARCH("V5",P263))),"A — 100%","B — sample ≥ 30%")
A264: DR-R5 | B264: Deck Engine spec | C264: OWNER-DIRECTED → CANON (R3/R5/R7/R9 strikeable) | D264: V5 — Failure-injection demonstration | F264: Dependency made unreachable or check made to error; observed refusal; no result returned; stale marker where degradation is the ruled posture | G264: A — 100% | K264: =IFERROR(INDEX('Status Map'!$B$2:$B$12,MATCH(C264,'Status Map'!$A$2:$A$12,0)),"UNDEFINED") | L264: COUNTS | M264: FIRST SENTENCE | P264: =IF(O264<>"",O264,LEFT(D264,2)) | Q264: =IF(O264<>"","Standards §6",IF(M264="HEADING ONLY","Derived from heading — PROVISIONAL",IF(M264="TEXT NOT IN REGISTRY","No text to derive from — PROVISIONAL","Derived from registered statement"))) | R264: =IF(OR(LEFT(G264,1)="A",L264="COUNTS",ISNUMBER(SEARCH("V1",P264)),ISNUMBER(SEARCH("V2",P264)),ISNUMBER(SEARCH("V5",P264))),"A — 100%","B — sample ≥ 30%")
A265: DR-R6 | B265: Deck Engine spec | C265: OWNER-DIRECTED → CANON (R3/R5/R7/R9 strikeable) | D265: V7 — Document & design inspection | F265: Specification text against implementation description; provenance sections; objective card lines | G265: B — sample ≥ 30% | K265: =IFERROR(INDEX('Status Map'!$B$2:$B$12,MATCH(C265,'Status Map'!$A$2:$A$12,0)),"UNDEFINED") | L265: COUNTS | M265: FIRST SENTENCE | P265: =IF(O265<>"",O265,LEFT(D265,2)) | Q265: =IF(O265<>"","Standards §6",IF(M265="HEADING ONLY","Derived from heading — PROVISIONAL",IF(M265="TEXT NOT IN REGISTRY","No text to derive from — PROVISIONAL","Derived from registered statement"))) | R265: =IF(OR(LEFT(G265,1)="A",L265="COUNTS",ISNUMBER(SEARCH("V1",P265)),ISNUMBER(SEARCH("V2",P265)),ISNUMBER(SEARCH("V5",P265))),"A — 100%","B — sample ≥ 30%")
A266: DR-R7 | B266: Deck Engine spec | C266: OWNER-DIRECTED → CANON (R3/R5/R7/R9 strikeable) | D266: V6 — Surface inspection | F266: DOM-bound substitution rule or harness receipt; fixed string verbatim; honest-gap variant rendered on null | G266: B — sample ≥ 30% | K266: =IFERROR(INDEX('Status Map'!$B$2:$B$12,MATCH(C266,'Status Map'!$A$2:$A$12,0)),"UNDEFINED") | L266: COUNTS | M266: FIRST SENTENCE | P266: =IF(O266<>"",O266,LEFT(D266,2)) | Q266: =IF(O266<>"","Standards §6",IF(M266="HEADING ONLY","Derived from heading — PROVISIONAL",IF(M266="TEXT NOT IN REGISTRY","No text to derive from — PROVISIONAL","Derived from registered statement"))) | R266: =IF(OR(LEFT(G266,1)="A",L266="COUNTS",ISNUMBER(SEARCH("V1",P266)),ISNUMBER(SEARCH("V2",P266)),ISNUMBER(SEARCH("V5",P266))),"A — 100%","B — sample ≥ 30%")
A267: DR-R8 | B267: Deck Engine spec | C267: OWNER-DIRECTED → CANON (R3/R5/R7/R9 strikeable) | D267: V4 — Governance-record evidence | F267: DECISIONS.md entry; ceremony record with tier, countersign, countdown, apply, re-verify; canon_ref present | G267: B — sample ≥ 30% | K267: =IFERROR(INDEX('Status Map'!$B$2:$B$12,MATCH(C267,'Status Map'!$A$2:$A$12,0)),"UNDEFINED") | L267: COUNTS | M267: FIRST SENTENCE | P267: =IF(O267<>"",O267,LEFT(D267,2)) | Q267: =IF(O267<>"","Standards §6",IF(M267="HEADING ONLY","Derived from heading — PROVISIONAL",IF(M267="TEXT NOT IN REGISTRY","No text to derive from — PROVISIONAL","Derived from registered statement"))) | R267: =IF(OR(LEFT(G267,1)="A",L267="COUNTS",ISNUMBER(SEARCH("V1",P267)),ISNUMBER(SEARCH("V2",P267)),ISNUMBER(SEARCH("V5",P267))),"A — 100%","B — sample ≥ 30%")
A268: DR-R9 | B268: Deck Engine spec | C268: OWNER-DIRECTED → CANON (R3/R5/R7/R9 strikeable) | D268: V7 — Document & design inspection | F268: Specification text against implementation description; provenance sections; objective card lines | G268: B — sample ≥ 30% | K268: =IFERROR(INDEX('Status Map'!$B$2:$B$12,MATCH(C268,'Status Map'!$A$2:$A$12,0)),"UNDEFINED") | L268: COUNTS | M268: FIRST SENTENCE | P268: =IF(O268<>"",O268,LEFT(D268,2)) | Q268: =IF(O268<>"","Standards §6",IF(M268="HEADING ONLY","Derived from heading — PROVISIONAL",IF(M268="TEXT NOT IN REGISTRY","No text to derive from — PROVISIONAL","Derived from registered statement"))) | R268: =IF(OR(LEFT(G268,1)="A",L268="COUNTS",ISNUMBER(SEARCH("V1",P268)),ISNUMBER(SEARCH("V2",P268)),ISNUMBER(SEARCH("V5",P268))),"A — 100%","B — sample ≥ 30%")
A269: A18.1 | B269: Doc 18 | C269: CANON | D269: V7 — Document & design inspection | F269: Specification text against implementation description; provenance sections; objective card lines | G269: B — sample ≥ 30% | K269: =IFERROR(INDEX('Status Map'!$B$2:$B$12,MATCH(C269,'Status Map'!$A$2:$A$12,0)),"UNDEFINED") | L269: =IFERROR(INDEX('Status Map'!$C$2:$C$12,MATCH(C269,'Status Map'!$A$2:$A$12,0)),"UNDEFINED") | M269: HEADING ONLY | P269: =IF(O269<>"",O269,LEFT(D269,2)) | Q269: =IF(O269<>"","Standards §6",IF(M269="HEADING ONLY","Derived from heading — PROVISIONAL",IF(M269="TEXT NOT IN REGISTRY","No text to derive from — PROVISIONAL","Derived from registered statement"))) | R269: =IF(OR(LEFT(G269,1)="A",L269="COUNTS",ISNUMBER(SEARCH("V1",P269)),ISNUMBER(SEARCH("V2",P269)),ISNUMBER(SEARCH("V5",P269))),"A — 100%","B — sample ≥ 30%")
A270: A18.2 | B270: Doc 18 | C270: CANON | D270: V7 — Document & design inspection | F270: Specification text against implementation description; provenance sections; objective card lines | G270: B — sample ≥ 30% | K270: =IFERROR(INDEX('Status Map'!$B$2:$B$12,MATCH(C270,'Status Map'!$A$2:$A$12,0)),"UNDEFINED") | L270: =IFERROR(INDEX('Status Map'!$C$2:$C$12,MATCH(C270,'Status Map'!$A$2:$A$12,0)),"UNDEFINED") | M270: HEADING ONLY | P270: =IF(O270<>"",O270,LEFT(D270,2)) | Q270: =IF(O270<>"","Standards §6",IF(M270="HEADING ONLY","Derived from heading — PROVISIONAL",IF(M270="TEXT NOT IN REGISTRY","No text to derive from — PROVISIONAL","Derived from registered statement"))) | R270: =IF(OR(LEFT(G270,1)="A",L270="COUNTS",ISNUMBER(SEARCH("V1",P270)),ISNUMBER(SEARCH("V2",P270)),ISNUMBER(SEARCH("V5",P270))),"A — 100%","B — sample ≥ 30%")
A271: A18.3 | B271: Doc 18 | C271: CANON | D271: V7 — Document & design inspection | F271: Specification text against implementation description; provenance sections; objective card lines | G271: B — sample ≥ 30% | K271: =IFERROR(INDEX('Status Map'!$B$2:$B$12,MATCH(C271,'Status Map'!$A$2:$A$12,0)),"UNDEFINED") | L271: =IFERROR(INDEX('Status Map'!$C$2:$C$12,MATCH(C271,'Status Map'!$A$2:$A$12,0)),"UNDEFINED") | M271: HEADING ONLY | P271: =IF(O271<>"",O271,LEFT(D271,2)) | Q271: =IF(O271<>"","Standards §6",IF(M271="HEADING ONLY","Derived from heading — PROVISIONAL",IF(M271="TEXT NOT IN REGISTRY","No text to derive from — PROVISIONAL","Derived from registered statement"))) | R271: =IF(OR(LEFT(G271,1)="A",L271="COUNTS",ISNUMBER(SEARCH("V1",P271)),ISNUMBER(SEARCH("V2",P271)),ISNUMBER(SEARCH("V5",P271))),"A — 100%","B — sample ≥ 30%")
A272: A18.4 | B272: Doc 18 | C272: CANON | D272: V5 — Failure-injection demonstration | F272: Dependency made unreachable or check made to error; observed refusal; no result returned; stale marker where degradation is the ruled posture | G272: A — 100% | K272: =IFERROR(INDEX('Status Map'!$B$2:$B$12,MATCH(C272,'Status Map'!$A$2:$A$12,0)),"UNDEFINED") | L272: =IFERROR(INDEX('Status Map'!$C$2:$C$12,MATCH(C272,'Status Map'!$A$2:$A$12,0)),"UNDEFINED") | M272: HEADING ONLY | P272: =IF(O272<>"",O272,LEFT(D272,2)) | Q272: =IF(O272<>"","Standards §6",IF(M272="HEADING ONLY","Derived from heading — PROVISIONAL",IF(M272="TEXT NOT IN REGISTRY","No text to derive from — PROVISIONAL","Derived from registered statement"))) | R272: =IF(OR(LEFT(G272,1)="A",L272="COUNTS",ISNUMBER(SEARCH("V1",P272)),ISNUMBER(SEARCH("V2",P272)),ISNUMBER(SEARCH("V5",P272))),"A — 100%","B — sample ≥ 30%")
A273: A18.5 | B273: Doc 18 | C273: CANON | D273: V7 — Document & design inspection | F273: Specification text against implementation description; provenance sections; objective card lines | G273: B — sample ≥ 30% | K273: =IFERROR(INDEX('Status Map'!$B$2:$B$12,MATCH(C273,'Status Map'!$A$2:$A$12,0)),"UNDEFINED") | L273: =IFERROR(INDEX('Status Map'!$C$2:$C$12,MATCH(C273,'Status Map'!$A$2:$A$12,0)),"UNDEFINED") | M273: HEADING ONLY | P273: =IF(O273<>"",O273,LEFT(D273,2)) | Q273: =IF(O273<>"","Standards §6",IF(M273="HEADING ONLY","Derived from heading — PROVISIONAL",IF(M273="TEXT NOT IN REGISTRY","No text to derive from — PROVISIONAL","Derived from registered statement"))) | R273: =IF(OR(LEFT(G273,1)="A",L273="COUNTS",ISNUMBER(SEARCH("V1",P273)),ISNUMBER(SEARCH("V2",P273)),ISNUMBER(SEARCH("V5",P273))),"A — 100%","B — sample ≥ 30%")
A274: A18.6 | B274: Doc 18 | C274: PROPOSED | D274: V7 — Document & design inspection | F274: Specification text against implementation description; provenance sections; objective card lines | G274: B — sample ≥ 30% | K274: =IFERROR(INDEX('Status Map'!$B$2:$B$12,MATCH(C274,'Status Map'!$A$2:$A$12,0)),"UNDEFINED") | L274: =IFERROR(INDEX('Status Map'!$C$2:$C$12,MATCH(C274,'Status Map'!$A$2:$A$12,0)),"UNDEFINED") | M274: HEADING ONLY | P274: =IF(O274<>"",O274,LEFT(D274,2)) | Q274: =IF(O274<>"","Standards §6",IF(M274="HEADING ONLY","Derived from heading — PROVISIONAL",IF(M274="TEXT NOT IN REGISTRY","No text to derive from — PROVISIONAL","Derived from registered statement"))) | R274: =IF(OR(LEFT(G274,1)="A",L274="COUNTS",ISNUMBER(SEARCH("V1",P274)),ISNUMBER(SEARCH("V2",P274)),ISNUMBER(SEARCH("V5",P274))),"A — 100%","B — sample ≥ 30%")
A275: A18.7 | B275: Doc 18 | C275: RULED | D275: V7 — Document & design inspection | F275: Specification text against implementation description; provenance sections; objective card lines | G275: B — sample ≥ 30% | K275: =IFERROR(INDEX('Status Map'!$B$2:$B$12,MATCH(C275,'Status Map'!$A$2:$A$12,0)),"UNDEFINED") | L275: =IFERROR(INDEX('Status Map'!$C$2:$C$12,MATCH(C275,'Status Map'!$A$2:$A$12,0)),"UNDEFINED") | M275: HEADING ONLY | P275: =IF(O275<>"",O275,LEFT(D275,2)) | Q275: =IF(O275<>"","Standards §6",IF(M275="HEADING ONLY","Derived from heading — PROVISIONAL",IF(M275="TEXT NOT IN REGISTRY","No text to derive from — PROVISIONAL","Derived from registered statement"))) | R275: =IF(OR(LEFT(G275,1)="A",L275="COUNTS",ISNUMBER(SEARCH("V1",P275)),ISNUMBER(SEARCH("V2",P275)),ISNUMBER(SEARCH("V5",P275))),"A — 100%","B — sample ≥ 30%")
A276: A18.8 | B276: Doc 18 | C276: OPEN | D276: V7 — Document & design inspection | F276: Specification text against implementation description; provenance sections; objective card lines | G276: B — sample ≥ 30% | K276: =IFERROR(INDEX('Status Map'!$B$2:$B$12,MATCH(C276,'Status Map'!$A$2:$A$12,0)),"UNDEFINED") | L276: =IFERROR(INDEX('Status Map'!$C$2:$C$12,MATCH(C276,'Status Map'!$A$2:$A$12,0)),"UNDEFINED") | M276: HEADING ONLY | P276: =IF(O276<>"",O276,LEFT(D276,2)) | Q276: =IF(O276<>"","Standards §6",IF(M276="HEADING ONLY","Derived from heading — PROVISIONAL",IF(M276="TEXT NOT IN REGISTRY","No text to derive from — PROVISIONAL","Derived from registered statement"))) | R276: =IF(OR(LEFT(G276,1)="A",L276="COUNTS",ISNUMBER(SEARCH("V1",P276)),ISNUMBER(SEARCH("V2",P276)),ISNUMBER(SEARCH("V5",P276))),"A — 100%","B — sample ≥ 30%")
A277: ROC-1 | B277: ROC spec | C277: PROPOSED (pending ratification) | D277: V7 — Document & design inspection | F277: Specification text against implementation description; provenance sections; objective card lines | G277: A — 100% | K277: =IFERROR(INDEX('Status Map'!$B$2:$B$12,MATCH(C277,'Status Map'!$A$2:$A$12,0)),"UNDEFINED") | L277: =IFERROR(INDEX('Status Map'!$C$2:$C$12,MATCH(C277,'Status Map'!$A$2:$A$12,0)),"UNDEFINED") | M277: STATEMENT AS REGISTERED | N277: C-6.6.4 | O277: V7 | P277: =IF(O277<>"",O277,LEFT(D277,2)) | Q277: =IF(O277<>"","Standards §6",IF(M277="HEADING ONLY","Derived from heading — PROVISIONAL",IF(M277="TEXT NOT IN REGISTRY","No text to derive from — PROVISIONAL","Derived from registered statement"))) | R277: =IF(OR(LEFT(G277,1)="A",L277="COUNTS",ISNUMBER(SEARCH("V1",P277)),ISNUMBER(SEARCH("V2",P277)),ISNUMBER(SEARCH("V5",P277))),"A — 100%","B — sample ≥ 30%")
A278: ROC-10 | B278: ROC spec | C278: PROPOSED (pending ratification) | D278: V7 — Document & design inspection | F278: Specification text against implementation description; provenance sections; objective card lines | G278: A — 100% | K278: =IFERROR(INDEX('Status Map'!$B$2:$B$12,MATCH(C278,'Status Map'!$A$2:$A$12,0)),"UNDEFINED") | L278: =IFERROR(INDEX('Status Map'!$C$2:$C$12,MATCH(C278,'Status Map'!$A$2:$A$12,0)),"UNDEFINED") | M278: STATEMENT AS REGISTERED | N278: C-6.6.4 | O278: V7 | P278: =IF(O278<>"",O278,LEFT(D278,2)) | Q278: =IF(O278<>"","Standards §6",IF(M278="HEADING ONLY","Derived from heading — PROVISIONAL",IF(M278="TEXT NOT IN REGISTRY","No text to derive from — PROVISIONAL","Derived from registered statement"))) | R278: =IF(OR(LEFT(G278,1)="A",L278="COUNTS",ISNUMBER(SEARCH("V1",P278)),ISNUMBER(SEARCH("V2",P278)),ISNUMBER(SEARCH("V5",P278))),"A — 100%","B — sample ≥ 30%")
A279: ROC-11 | B279: ROC spec | C279: PROPOSED (pending ratification) | D279: V3 — Record evidence | F279: Ledger rows inspected; hash-chain verifier receipt; refused operations present on identical terms | G279: A — 100% | K279: =IFERROR(INDEX('Status Map'!$B$2:$B$12,MATCH(C279,'Status Map'!$A$2:$A$12,0)),"UNDEFINED") | L279: =IFERROR(INDEX('Status Map'!$C$2:$C$12,MATCH(C279,'Status Map'!$A$2:$A$12,0)),"UNDEFINED") | M279: STATEMENT AS REGISTERED | N279: C-6.6.4 | O279: V7 | P279: =IF(O279<>"",O279,LEFT(D279,2)) | Q279: =IF(O279<>"","Standards §6",IF(M279="HEADING ONLY","Derived from heading — PROVISIONAL",IF(M279="TEXT NOT IN REGISTRY","No text to derive from — PROVISIONAL","Derived from registered statement"))) | R279: =IF(OR(LEFT(G279,1)="A",L279="COUNTS",ISNUMBER(SEARCH("V1",P279)),ISNUMBER(SEARCH("V2",P279)),ISNUMBER(SEARCH("V5",P279))),"A — 100%","B — sample ≥ 30%")
A280: ROC-2 | B280: ROC spec | C280: PROPOSED (pending ratification) | D280: V4 — Governance-record evidence | F280: DECISIONS.md entry; ceremony record with tier, countersign, countdown, apply, re-verify; canon_ref present | G280: A — 100% | K280: =IFERROR(INDEX('Status Map'!$B$2:$B$12,MATCH(C280,'Status Map'!$A$2:$A$12,0)),"UNDEFINED") | L280: =IFERROR(INDEX('Status Map'!$C$2:$C$12,MATCH(C280,'Status Map'!$A$2:$A$12,0)),"UNDEFINED") | M280: STATEMENT AS REGISTERED | N280: C-6.6.4 | O280: V7 | P280: =IF(O280<>"",O280,LEFT(D280,2)) | Q280: =IF(O280<>"","Standards §6",IF(M280="HEADING ONLY","Derived from heading — PROVISIONAL",IF(M280="TEXT NOT IN REGISTRY","No text to derive from — PROVISIONAL","Derived from registered statement"))) | R280: =IF(OR(LEFT(G280,1)="A",L280="COUNTS",ISNUMBER(SEARCH("V1",P280)),ISNUMBER(SEARCH("V2",P280)),ISNUMBER(SEARCH("V5",P280))),"A — 100%","B — sample ≥ 30%")
A281: ROC-3 | B281: ROC spec | C281: PROPOSED (pending ratification) | D281: V7 — Document & design inspection | F281: Specification text against implementation description; provenance sections; objective card lines | G281: A — 100% | K281: =IFERROR(INDEX('Status Map'!$B$2:$B$12,MATCH(C281,'Status Map'!$A$2:$A$12,0)),"UNDEFINED") | L281: =IFERROR(INDEX('Status Map'!$C$2:$C$12,MATCH(C281,'Status Map'!$A$2:$A$12,0)),"UNDEFINED") | M281: STATEMENT AS REGISTERED | N281: C-6.6.4 | O281: V7 | P281: =IF(O281<>"",O281,LEFT(D281,2)) | Q281: =IF(O281<>"","Standards §6",IF(M281="HEADING ONLY","Derived from heading — PROVISIONAL",IF(M281="TEXT NOT IN REGISTRY","No text to derive from — PROVISIONAL","Derived from registered statement"))) | R281: =IF(OR(LEFT(G281,1)="A",L281="COUNTS",ISNUMBER(SEARCH("V1",P281)),ISNUMBER(SEARCH("V2",P281)),ISNUMBER(SEARCH("V5",P281))),"A — 100%","B — sample ≥ 30%")
A282: ROC-4 | B282: ROC spec | C282: PROPOSED (pending ratification) | D282: V7 — Document & design inspection | F282: Specification text against implementation description; provenance sections; objective card lines | G282: A — 100% | K282: =IFERROR(INDEX('Status Map'!$B$2:$B$12,MATCH(C282,'Status Map'!$A$2:$A$12,0)),"UNDEFINED") | L282: =IFERROR(INDEX('Status Map'!$C$2:$C$12,MATCH(C282,'Status Map'!$A$2:$A$12,0)),"UNDEFINED") | M282: STATEMENT AS REGISTERED | N282: C-6.6.4 | O282: V7 | P282: =IF(O282<>"",O282,LEFT(D282,2)) | Q282: =IF(O282<>"","Standards §6",IF(M282="HEADING ONLY","Derived from heading — PROVISIONAL",IF(M282="TEXT NOT IN REGISTRY","No text to derive from — PROVISIONAL","Derived from registered statement"))) | R282: =IF(OR(LEFT(G282,1)="A",L282="COUNTS",ISNUMBER(SEARCH("V1",P282)),ISNUMBER(SEARCH("V2",P282)),ISNUMBER(SEARCH("V5",P282))),"A — 100%","B — sample ≥ 30%")
A283: ROC-5 | B283: ROC spec | C283: PROPOSED (pending ratification) | D283: V7 — Document & design inspection | F283: Specification text against implementation description; provenance sections; objective card lines | G283: A — 100% | K283: =IFERROR(INDEX('Status Map'!$B$2:$B$12,MATCH(C283,'Status Map'!$A$2:$A$12,0)),"UNDEFINED") | L283: =IFERROR(INDEX('Status Map'!$C$2:$C$12,MATCH(C283,'Status Map'!$A$2:$A$12,0)),"UNDEFINED") | M283: STATEMENT AS REGISTERED | N283: C-6.6.4 | O283: V7 | P283: =IF(O283<>"",O283,LEFT(D283,2)) | Q283: =IF(O283<>"","Standards §6",IF(M283="HEADING ONLY","Derived from heading — PROVISIONAL",IF(M283="TEXT NOT IN REGISTRY","No text to derive from — PROVISIONAL","Derived from registered statement"))) | R283: =IF(OR(LEFT(G283,1)="A",L283="COUNTS",ISNUMBER(SEARCH("V1",P283)),ISNUMBER(SEARCH("V2",P283)),ISNUMBER(SEARCH("V5",P283))),"A — 100%","B — sample ≥ 30%")
A284: ROC-6 | B284: ROC spec | C284: PROPOSED (pending ratification) | D284: V7 — Document & design inspection | F284: Specification text against implementation description; provenance sections; objective card lines | G284: A — 100% | K284: =IFERROR(INDEX('Status Map'!$B$2:$B$12,MATCH(C284,'Status Map'!$A$2:$A$12,0)),"UNDEFINED") | L284: =IFERROR(INDEX('Status Map'!$C$2:$C$12,MATCH(C284,'Status Map'!$A$2:$A$12,0)),"UNDEFINED") | M284: STATEMENT AS REGISTERED | N284: C-6.6.4 | O284: V7 | P284: =IF(O284<>"",O284,LEFT(D284,2)) | Q284: =IF(O284<>"","Standards §6",IF(M284="HEADING ONLY","Derived from heading — PROVISIONAL",IF(M284="TEXT NOT IN REGISTRY","No text to derive from — PROVISIONAL","Derived from registered statement"))) | R284: =IF(OR(LEFT(G284,1)="A",L284="COUNTS",ISNUMBER(SEARCH("V1",P284)),ISNUMBER(SEARCH("V2",P284)),ISNUMBER(SEARCH("V5",P284))),"A — 100%","B — sample ≥ 30%")
A285: ROC-7 | B285: ROC spec | C285: PROPOSED (pending ratification) | D285: V7 — Document & design inspection | F285: Specification text against implementation description; provenance sections; objective card lines | G285: A — 100% | K285: =IFERROR(INDEX('Status Map'!$B$2:$B$12,MATCH(C285,'Status Map'!$A$2:$A$12,0)),"UNDEFINED") | L285: =IFERROR(INDEX('Status Map'!$C$2:$C$12,MATCH(C285,'Status Map'!$A$2:$A$12,0)),"UNDEFINED") | M285: STATEMENT AS REGISTERED | N285: C-6.6.4 | O285: V7 | P285: =IF(O285<>"",O285,LEFT(D285,2)) | Q285: =IF(O285<>"","Standards §6",IF(M285="HEADING ONLY","Derived from heading — PROVISIONAL",IF(M285="TEXT NOT IN REGISTRY","No text to derive from — PROVISIONAL","Derived from registered statement"))) | R285: =IF(OR(LEFT(G285,1)="A",L285="COUNTS",ISNUMBER(SEARCH("V1",P285)),ISNUMBER(SEARCH("V2",P285)),ISNUMBER(SEARCH("V5",P285))),"A — 100%","B — sample ≥ 30%")
A286: ROC-8 | B286: ROC spec | C286: PROPOSED (pending ratification) | D286: V7 — Document & design inspection | F286: Specification text against implementation description; provenance sections; objective card lines | G286: A — 100% | K286: =IFERROR(INDEX('Status Map'!$B$2:$B$12,MATCH(C286,'Status Map'!$A$2:$A$12,0)),"UNDEFINED") | L286: =IFERROR(INDEX('Status Map'!$C$2:$C$12,MATCH(C286,'Status Map'!$A$2:$A$12,0)),"UNDEFINED") | M286: STATEMENT AS REGISTERED | N286: C-6.6.4 | O286: V7 | P286: =IF(O286<>"",O286,LEFT(D286,2)) | Q286: =IF(O286<>"","Standards §6",IF(M286="HEADING ONLY","Derived from heading — PROVISIONAL",IF(M286="TEXT NOT IN REGISTRY","No text to derive from — PROVISIONAL","Derived from registered statement"))) | R286: =IF(OR(LEFT(G286,1)="A",L286="COUNTS",ISNUMBER(SEARCH("V1",P286)),ISNUMBER(SEARCH("V2",P286)),ISNUMBER(SEARCH("V5",P286))),"A — 100%","B — sample ≥ 30%")
A287: ROC-9 | B287: ROC spec | C287: PROPOSED (pending ratification) | D287: V7 — Document & design inspection | F287: Specification text against implementation description; provenance sections; objective card lines | G287: A — 100% | K287: =IFERROR(INDEX('Status Map'!$B$2:$B$12,MATCH(C287,'Status Map'!$A$2:$A$12,0)),"UNDEFINED") | L287: =IFERROR(INDEX('Status Map'!$C$2:$C$12,MATCH(C287,'Status Map'!$A$2:$A$12,0)),"UNDEFINED") | M287: STATEMENT AS REGISTERED | N287: C-6.6.4 | O287: V7 | P287: =IF(O287<>"",O287,LEFT(D287,2)) | Q287: =IF(O287<>"","Standards §6",IF(M287="HEADING ONLY","Derived from heading — PROVISIONAL",IF(M287="TEXT NOT IN REGISTRY","No text to derive from — PROVISIONAL","Derived from registered statement"))) | R287: =IF(OR(LEFT(G287,1)="A",L287="COUNTS",ISNUMBER(SEARCH("V1",P287)),ISNUMBER(SEARCH("V2",P287)),ISNUMBER(SEARCH("V5",P287))),"A — 100%","B — sample ≥ 30%")
A288: RBM-1 | B288: Rules Service spec | C288: PROPOSED | D288: V5 — Failure-injection demonstration | F288: Dependency made unreachable or check made to error; observed refusal; no result returned; stale marker where degradation is the ruled posture | G288: A — 100% | K288: =IFERROR(INDEX('Status Map'!$B$2:$B$12,MATCH(C288,'Status Map'!$A$2:$A$12,0)),"UNDEFINED") | L288: =IFERROR(INDEX('Status Map'!$C$2:$C$12,MATCH(C288,'Status Map'!$A$2:$A$12,0)),"UNDEFINED") | M288: STATEMENT AS REGISTERED | P288: =IF(O288<>"",O288,LEFT(D288,2)) | Q288: =IF(O288<>"","Standards §6",IF(M288="HEADING ONLY","Derived from heading — PROVISIONAL",IF(M288="TEXT NOT IN REGISTRY","No text to derive from — PROVISIONAL","Derived from registered statement"))) | R288: =IF(OR(LEFT(G288,1)="A",L288="COUNTS",ISNUMBER(SEARCH("V1",P288)),ISNUMBER(SEARCH("V2",P288)),ISNUMBER(SEARCH("V5",P288))),"A — 100%","B — sample ≥ 30%")
A289: RBM-2 | B289: Rules Service spec | C289: PROPOSED | D289: V7 — Document & design inspection | F289: Specification text against implementation description; provenance sections; objective card lines | G289: A — 100% | K289: =IFERROR(INDEX('Status Map'!$B$2:$B$12,MATCH(C289,'Status Map'!$A$2:$A$12,0)),"UNDEFINED") | L289: =IFERROR(INDEX('Status Map'!$C$2:$C$12,MATCH(C289,'Status Map'!$A$2:$A$12,0)),"UNDEFINED") | M289: STATEMENT AS REGISTERED | P289: =IF(O289<>"",O289,LEFT(D289,2)) | Q289: =IF(O289<>"","Standards §6",IF(M289="HEADING ONLY","Derived from heading — PROVISIONAL",IF(M289="TEXT NOT IN REGISTRY","No text to derive from — PROVISIONAL","Derived from registered statement"))) | R289: =IF(OR(LEFT(G289,1)="A",L289="COUNTS",ISNUMBER(SEARCH("V1",P289)),ISNUMBER(SEARCH("V2",P289)),ISNUMBER(SEARCH("V5",P289))),"A — 100%","B — sample ≥ 30%")
A290: RBM-3 | B290: Rules Service spec | C290: PROPOSED | D290: V5 — Failure-injection demonstration | F290: Dependency made unreachable or check made to error; observed refusal; no result returned; stale marker where degradation is the ruled posture | G290: A — 100% | K290: =IFERROR(INDEX('Status Map'!$B$2:$B$12,MATCH(C290,'Status Map'!$A$2:$A$12,0)),"UNDEFINED") | L290: =IFERROR(INDEX('Status Map'!$C$2:$C$12,MATCH(C290,'Status Map'!$A$2:$A$12,0)),"UNDEFINED") | M290: STATEMENT AS REGISTERED | P290: =IF(O290<>"",O290,LEFT(D290,2)) | Q290: =IF(O290<>"","Standards §6",IF(M290="HEADING ONLY","Derived from heading — PROVISIONAL",IF(M290="TEXT NOT IN REGISTRY","No text to derive from — PROVISIONAL","Derived from registered statement"))) | R290: =IF(OR(LEFT(G290,1)="A",L290="COUNTS",ISNUMBER(SEARCH("V1",P290)),ISNUMBER(SEARCH("V2",P290)),ISNUMBER(SEARCH("V5",P290))),"A — 100%","B — sample ≥ 30%")
A291: RBM-4 | B291: Rules Service spec | C291: PROPOSED | D291: V7 — Document & design inspection | F291: Specification text against implementation description; provenance sections; objective card lines | G291: A — 100% | K291: =IFERROR(INDEX('Status Map'!$B$2:$B$12,MATCH(C291,'Status Map'!$A$2:$A$12,0)),"UNDEFINED") | L291: =IFERROR(INDEX('Status Map'!$C$2:$C$12,MATCH(C291,'Status Map'!$A$2:$A$12,0)),"UNDEFINED") | M291: STATEMENT AS REGISTERED | P291: =IF(O291<>"",O291,LEFT(D291,2)) | Q291: =IF(O291<>"","Standards §6",IF(M291="HEADING ONLY","Derived from heading — PROVISIONAL",IF(M291="TEXT NOT IN REGISTRY","No text to derive from — PROVISIONAL","Derived from registered statement"))) | R291: =IF(OR(LEFT(G291,1)="A",L291="COUNTS",ISNUMBER(SEARCH("V1",P291)),ISNUMBER(SEARCH("V2",P291)),ISNUMBER(SEARCH("V5",P291))),"A — 100%","B — sample ≥ 30%")
A292: RBM-5 | B292: Rules Service spec | C292: PROPOSED | D292: V4 — Governance-record evidence | F292: DECISIONS.md entry; ceremony record with tier, countersign, countdown, apply, re-verify; canon_ref present | G292: A — 100% | K292: =IFERROR(INDEX('Status Map'!$B$2:$B$12,MATCH(C292,'Status Map'!$A$2:$A$12,0)),"UNDEFINED") | L292: =IFERROR(INDEX('Status Map'!$C$2:$C$12,MATCH(C292,'Status Map'!$A$2:$A$12,0)),"UNDEFINED") | M292: STATEMENT AS REGISTERED | P292: =IF(O292<>"",O292,LEFT(D292,2)) | Q292: =IF(O292<>"","Standards §6",IF(M292="HEADING ONLY","Derived from heading — PROVISIONAL",IF(M292="TEXT NOT IN REGISTRY","No text to derive from — PROVISIONAL","Derived from registered statement"))) | R292: =IF(OR(LEFT(G292,1)="A",L292="COUNTS",ISNUMBER(SEARCH("V1",P292)),ISNUMBER(SEARCH("V2",P292)),ISNUMBER(SEARCH("V5",P292))),"A — 100%","B — sample ≥ 30%")
A293: RBM-6 | B293: Rules Service spec | C293: PROPOSED | D293: V5 — Failure-injection demonstration | F293: Dependency made unreachable or check made to error; observed refusal; no result returned; stale marker where degradation is the ruled posture | G293: A — 100% | K293: =IFERROR(INDEX('Status Map'!$B$2:$B$12,MATCH(C293,'Status Map'!$A$2:$A$12,0)),"UNDEFINED") | L293: =IFERROR(INDEX('Status Map'!$C$2:$C$12,MATCH(C293,'Status Map'!$A$2:$A$12,0)),"UNDEFINED") | M293: STATEMENT AS REGISTERED | P293: =IF(O293<>"",O293,LEFT(D293,2)) | Q293: =IF(O293<>"","Standards §6",IF(M293="HEADING ONLY","Derived from heading — PROVISIONAL",IF(M293="TEXT NOT IN REGISTRY","No text to derive from — PROVISIONAL","Derived from registered statement"))) | R293: =IF(OR(LEFT(G293,1)="A",L293="COUNTS",ISNUMBER(SEARCH("V1",P293)),ISNUMBER(SEARCH("V2",P293)),ISNUMBER(SEARCH("V5",P293))),"A — 100%","B — sample ≥ 30%")
A294: RBM-7 | B294: Rules Service spec | C294: PROPOSED | D294: V4 — Governance-record evidence | F294: DECISIONS.md entry; ceremony record with tier, countersign, countdown, apply, re-verify; canon_ref present | G294: A — 100% | K294: =IFERROR(INDEX('Status Map'!$B$2:$B$12,MATCH(C294,'Status Map'!$A$2:$A$12,0)),"UNDEFINED") | L294: =IFERROR(INDEX('Status Map'!$C$2:$C$12,MATCH(C294,'Status Map'!$A$2:$A$12,0)),"UNDEFINED") | M294: STATEMENT AS REGISTERED | N294: C-6.6.1 | O294: V4 | P294: =IF(O294<>"",O294,LEFT(D294,2)) | Q294: =IF(O294<>"","Standards §6",IF(M294="HEADING ONLY","Derived from heading — PROVISIONAL",IF(M294="TEXT NOT IN REGISTRY","No text to derive from — PROVISIONAL","Derived from registered statement"))) | R294: =IF(OR(LEFT(G294,1)="A",L294="COUNTS",ISNUMBER(SEARCH("V1",P294)),ISNUMBER(SEARCH("V2",P294)),ISNUMBER(SEARCH("V5",P294))),"A — 100%","B — sample ≥ 30%")
A295: RBM-8 | B295: Rules Service spec | C295: PROPOSED | D295: V4 — Governance-record evidence | F295: DECISIONS.md entry; ceremony record with tier, countersign, countdown, apply, re-verify; canon_ref present | G295: A — 100% | K295: =IFERROR(INDEX('Status Map'!$B$2:$B$12,MATCH(C295,'Status Map'!$A$2:$A$12,0)),"UNDEFINED") | L295: =IFERROR(INDEX('Status Map'!$C$2:$C$12,MATCH(C295,'Status Map'!$A$2:$A$12,0)),"UNDEFINED") | M295: STATEMENT AS REGISTERED | N295: C-6.6.1, C-6.6.2 | O295: V4 + V5 | P295: =IF(O295<>"",O295,LEFT(D295,2)) | Q295: =IF(O295<>"","Standards §6",IF(M295="HEADING ONLY","Derived from heading — PROVISIONAL",IF(M295="TEXT NOT IN REGISTRY","No text to derive from — PROVISIONAL","Derived from registered statement"))) | R295: =IF(OR(LEFT(G295,1)="A",L295="COUNTS",ISNUMBER(SEARCH("V1",P295)),ISNUMBER(SEARCH("V2",P295)),ISNUMBER(SEARCH("V5",P295))),"A — 100%","B — sample ≥ 30%")
A296: RBM-9 | B296: Rules Service spec | C296: PROPOSED | D296: V3 — Record evidence | F296: Ledger rows inspected; hash-chain verifier receipt; refused operations present on identical terms | G296: A — 100% | K296: =IFERROR(INDEX('Status Map'!$B$2:$B$12,MATCH(C296,'Status Map'!$A$2:$A$12,0)),"UNDEFINED") | L296: =IFERROR(INDEX('Status Map'!$C$2:$C$12,MATCH(C296,'Status Map'!$A$2:$A$12,0)),"UNDEFINED") | M296: STATEMENT AS REGISTERED | P296: =IF(O296<>"",O296,LEFT(D296,2)) | Q296: =IF(O296<>"","Standards §6",IF(M296="HEADING ONLY","Derived from heading — PROVISIONAL",IF(M296="TEXT NOT IN REGISTRY","No text to derive from — PROVISIONAL","Derived from registered statement"))) | R296: =IF(OR(LEFT(G296,1)="A",L296="COUNTS",ISNUMBER(SEARCH("V1",P296)),ISNUMBER(SEARCH("V2",P296)),ISNUMBER(SEARCH("V5",P296))),"A — 100%","B — sample ≥ 30%")
A297: RBM-10 | B297: Rules Service spec | C297: PROPOSED | D297: V3 — Record evidence | F297: Ledger rows inspected; hash-chain verifier receipt; refused operations present on identical terms | G297: A — 100% | K297: =IFERROR(INDEX('Status Map'!$B$2:$B$12,MATCH(C297,'Status Map'!$A$2:$A$12,0)),"UNDEFINED") | L297: =IFERROR(INDEX('Status Map'!$C$2:$C$12,MATCH(C297,'Status Map'!$A$2:$A$12,0)),"UNDEFINED") | M297: STATEMENT AS REGISTERED | P297: =IF(O297<>"",O297,LEFT(D297,2)) | Q297: =IF(O297<>"","Standards §6",IF(M297="HEADING ONLY","Derived from heading — PROVISIONAL",IF(M297="TEXT NOT IN REGISTRY","No text to derive from — PROVISIONAL","Derived from registered statement"))) | R297: =IF(OR(LEFT(G297,1)="A",L297="COUNTS",ISNUMBER(SEARCH("V1",P297)),ISNUMBER(SEARCH("V2",P297)),ISNUMBER(SEARCH("V5",P297))),"A — 100%","B — sample ≥ 30%")
...

Sheet Status Map
A1: Raw status (as registered) | B1: Normalised status | C1: Weight in promise roll-up | D1: Rows | E1: Basis / owner action
A2: CANON | B2: CANON | C2: COUNTS | D2: =COUNTIF('QA Verification'!$C$2:$C$603,A2) | E2: Ratified.
A3: RULED | B3: RULED | C3: COUNTS | D3: =COUNTIF('QA Verification'!$C$2:$C$603,A3) | E3: Ratified by ruling. The DECISIONS.md entry is confirmed by the auditor before the rule is weighed (Standards 2.5).
A4: PROPOSED | B4: PROPOSED | C4: UNRATIFIED | D4: =COUNTIF('QA Verification'!$C$2:$C$603,A4) | E4: Examined and given a verdict; excluded from the ratified roll-up, included in the full roll-up.
A5: PROPOSED (pending ratification) | B5: PROPOSED | C5: UNRATIFIED | D5: =COUNTIF('QA Verification'!$C$2:$C$603,A5) | E5: As PROPOSED.
A6: DEFAULT (draft; R2 open) | B6: DEFAULT | C6: UNRATIFIED | D6: =COUNTIF('QA Verification'!$C$2:$C$603,A6) | E6: As PROPOSED.
A7: OPEN | B7: OPEN | C7: OPEN | D7: =COUNTIF('QA Verification'!$C$2:$C$603,A7) | E7: Recorded NOT EXAMINED with reason OPEN.
A8: — | B8: UNDEFINED | C8: UNDEFINED | D8: =COUNTIF('QA Verification'!$C$2:$C$603,A8) | E8: OWNER ACTION: status not in the vocabulary. Rule CANON, RULED, PROPOSED, DEFAULT or OPEN before the audit target is tagged. Until ruled: examined, excluded from the ratified roll-up, listed in the registry-defect annex.
A9: — (see heading) | B9: UNDEFINED | C9: UNDEFINED | D9: =COUNTIF('QA Verification'!$C$2:$C$603,A9) | E9: OWNER ACTION: as above. The status is said to sit in the source heading; transcribe it.
A10: See xlsx | B10: UNDEFINED | C10: UNDEFINED | D10: =COUNTIF('QA Verification'!$C$2:$C$603,A10) | E10: OWNER ACTION: status and text sit in Security_Assurance_Promise_Set.xlsx, which was not issued with the registries. Supply it (Standards 9.1) and transcribe the status.
A11: DETERMINED | B11: RULED | C11: COUNTS | D11: =COUNTIF('QA Verification'!$C$2:$C$603,A11) | E11: Owner ruling 21 Sep 2026: a determination and an owner-directed canon entry are ratified acts; weight COUNTS.
A12: OWNER-DIRECTED → CANON (R3/R5/R7/R9 strikeable) | B12: RULED | C12: COUNTS | D12: =COUNTIF('QA Verification'!$C$2:$C$603,A12) | E12: Owner ruling 21 Sep 2026: a determination and an owner-directed canon entry are ratified acts; weight COUNTS.
A13: Total | D13: =SUM(D2:D12)
A15: Columns B and C are the only place status weight is set. Edit them here and every derived column in QA Verification, and the Audit Summary, recalculates. Yellow = input; grey = formula.

Sheet Check Register
A1: Check ID | B1: Part | C1: Domain | D1: Check | E1: Standard | F1: Class / method | G1: FAIL or DEFECT looks like | H1: Registry rules resolved (document-qualified) | I1: Citations that do not resolve in the registry | J1: Verdict / rating | K1: Evidence examined (class · artefact) | L1: Observed | M1: Severity | N1: Finding ref | O1: Commit · ratchet
A2: C-6.1.1 | B2: I Conformance | C2: 6.1 Build discipline | D2: Every seal is a §3.3 three-commit seal; Commit-B and Commit-C bank the prior SHA | E2: SO §3.3 | F2: V4 | G2: A seal with an unbanked SHA; a fixup that rewrites history
A3: C-6.1.2 | B3: I Conformance | C3: 6.1 Build discipline | D3: Full BASELINE_GUARD=1 sweep before Commit-B; byte-identical double-green recorded | E3: SO §3.3; R-18 close standard | F3: V1 | G3: A seal note showing targeted invariants only
A4: C-6.1.3 | B4: I Conformance | C4: 6.1 Build discipline | D4: Ratchet floor moves only from measurement, reconciled line by line; no silent rebaselining | E4: SO §3 | F4: V4 | G4: A floor bump without a reconciliation record
A5: C-6.1.4 | B5: I Conformance | C5: 6.1 Build discipline | D5: Every generated requirement carries canon_ref; the documentation check fails on its absence | E5: R-18 effect 2 | F5: V4 | G5: A requirements file with a row lacking canon_ref and passing CI
A6: C-6.1.5 | B6: I Conformance | C6: 6.1 Build discipline | D6: Every milestone has a pinned objective card; every seal cites a card line | E6: SO §6.2 | F6: V4 | G6: A seal message citing no line; a card whose MUST-DO has no exit evidence
A7: C-6.1.6 | B7: I Conformance | C7: 6.1 Build discipline | D7: A gate-satisfaction claim cites absence-of-blocker evidence per line | E7: SO §6.2 amendment | F7: V4 | G7: “Gate satisfied” resting on “waves closed” alone
A8: C-6.1.7 | B8: I Conformance | C8: 6.1 Build discipline | D8: Order of authority observed: no lower layer amends a higher one | E8: R-18 effect 1 | F8: V7 | G8: An SER clause contradicting a CANON rule with no erratum
A9: C-6.2.1 | B9: I Conformance | C9: 6.2 Trusted computing base and determinism | D9: Membership test is BA-1.1: deterministic and failure falsifies a stated guarantee | E9: Doc 0 BA-1.1; R-18 effect 7 | F9: V7 | G9: A membership table using a different test | I9: Doc 0 BA-1.1 — no registry row
A10: C-6.2.2 | B10: I Conformance | C10: 6.2 Trusted computing base and determinism | D10: Every enumerated member has a golden-input, byte-identical test | E10: B.8; tcb_enumeration_v1; determinism_inventory_v1 (v1.0 cited DET-1, DET-2 — miscited, RD-06) | F10: V1 | G10: A member with no test, or a test without a stated golden input | I10: B.8 — no registry row; DET-1 — DET-1 in the registry is an OPEN item on a CIF halt mechanism, not a golden-input test rule; DET-2 — DET-2 in the registry concerns Mtafiti classification confirmation, not a golden-input test rule
A11: C-6.2.3 | B11: I Conformance | C11: 6.2 Trusted computing base and determinism | D11: No learned component participates in any TCB decision | E11: Attribute 10 | F11: V2 | G11: A model output reachable by a decision function
A12: C-6.2.4 | B12: I Conformance | C12: 6.2 Trusted computing base and determinism | D12: Every member refuses when its own check cannot complete | E12: FP-1, FP-2 | F12: V5 | G12: A member returning a result under injected failure | H12: failure_posture_v1 · FP-1; failure_posture_v1 · FP-2
A13: C-6.2.5 | B13: I Conformance | C13: 6.2 Trusted computing base and determinism | D13: Components in the build but outside the enumeration are absent | E13: tcb_enumeration_v1 method | F13: V7 | G13: A decision-bearing component not in the table
A14: C-6.3.1 | B14: I Conformance | C14: 6.3 The chokepoint and custody | D14: Exactly one function invokes the external model client; the build fails on a second | E14: Doc 1 A5.1 | F14: V2 | G14: A second call site, an import outside the allow-list, or a scan that misses call sites | H14: Doc 1 · A5.1
A15: C-6.3.2 | B15: I Conformance | C15: 6.3 The chokepoint and custody | D15: Custody sequence runs on every call: mask before send, re-identify only inside | E15: DAP-7 | F15: V1 + V5 | G15: A path on which masking is conditional or skippable | H15: DAP Backend spec · DAP-7
A16: C-6.3.3 | B16: I Conformance | C16: 6.3 The chokepoint and custody | D16: No parameter on invoke() alters whether custody runs; tenant_id is required, never Optional | E16: DAP-7 Option D ruling | F16: V2 | G16: A bypass-shaped parameter; an Optional tenant scope | H16: DAP Backend spec · DAP-7
A17: C-6.3.4 | B17: I Conformance | C17: 6.3 The chokepoint and custody | D17: Outbound network is allow-listed; unlisted destinations refuse | E17: Doc 1; ENT-18 | F17: V5 | G17: A connection to an unlisted host succeeding | H17: entitlement_service_v1 · ENT-18
A18: C-6.3.5 | B18: I Conformance | C18: 6.3 The chokepoint and custody | D18: Crossing policy is integrity-verified at load; unverifiable policy is a closed gate | E18: SEC-1 | F18: V5 | G18: A tampered policy loading | H18: security_architecture_v1 · SEC-1
A19: C-6.3.6 | B19: I Conformance | C19: 6.3 The chokepoint and custody | D19: Every crossing is receipted with provider and model version | E19: Doc 1 A5.7; V-4 | F19: V3 | G19: A crossing with no row, or a row without provider and version | H19: Doc 1 · A5.7
A20: C-6.3.7 | B20: I Conformance | C20: 6.3 The chokepoint and custody | D20: Every crossing event reaches the Watch input seat before the call returns; an unobservable crossing does not happen | E20: Doc 3 A3; W1f ruling | F20: V5 | G20: A call completing with the seat unreachable | I20: Doc 3 A3 — no registry row
A21: C-6.4.1 | B21: I Conformance | C21: 6.4 The Watch | D21: Grey Mirror can assert facts and cannot block, throttle, notify, or act | E21: Doc 3 A2 | F21: V2 | G21: A detection component with an action path | I21: Doc 3 A2 — no registry row
A22: C-6.4.2 | B22: I Conformance | C22: 6.4 The Watch | D22: Mkono acts only on a verdict whose signature verifies | E22: SER C.3.5 I-1; R-18 effect 3 | F22: V1 + V5 | G22: An action taken on an unsigned or unverified verdict
A23: C-6.4.3 | B23: I Conformance | C23: 6.4 The Watch | D23: The verdict schema has no confidence, score, strength, or probability field; certificate is evidence only | E23: Doc 3 A5.2; watch_learning_v1 A5.19 | F23: V2 + V6 | G23: Any numeric field on the verdict that enters the action decision | H23: Doc 3 · A5.2; watch_learning_v1 · A5.19
A24: C-6.4.4 | B24: I Conformance | C24: 6.4 The Watch | D24: Severance keys to the closed signal registry; the registry is changed only by ceremony | E24: Doc 3 A5.2; watch_learning_v1 A5.20; RBM-23 | F24: V4 | G24: A severance triggered from outside the registry; a registry edit without a ceremony record | H24: Doc 3 · A5.2; watch_learning_v1 · A5.20; watch_learning_v1 · RBM-23
A25: C-6.4.5 | B25: I Conformance | C25: 6.4 The Watch | D25: Response ladder is annotate · shape · contain · sever; destroy does not exist | E25: Doc 3 A5.3; T-c ruling | F25: V2 | G25: A “destroy” action class in any schema or code path | H25: Doc 3 · A5.3
A26: C-6.4.6 | B26: I Conformance | C26: 6.4 The Watch | D26: Contain and sever freeze the session; the runtime is not deleted | E26: AC-13; R-18 effect 6 | F26: V5 | G26: A sever that removes the runtime pod | H26: serving_integrity_v1 · AC-13
A27: C-6.4.7 | B27: I Conformance | C27: 6.4 The Watch | D27: Every automatic action is reversible and time-limited; blast budget enforced | E27: Doc 3 A5.3, Doc 3 A5.14 | F27: V5 | G27: An automatic action with no expiry or no reversal path | H27: Doc 3 · A5.3; Doc 3 · A5.14
A28: C-6.4.8 | B28: I Conformance | C28: 6.4 The Watch | D28: Certificate requirements are system-TCB class; the ratifying human is named | E28: watch_learning_v1 A5.20; R-16 | F28: V4 | G28: A requirement admitted without the ceremony or the named ratifier | H28: watch_learning_v1 · A5.20
A29: C-6.5.1 | B29: I Conformance | C29: 6.5 The Ledger | D29: Single writer; hash chain intact; append-only — no update or delete path | E29: Doc 5; B.4; BR-8.1 | F29: V2 + V3 | G29: A second writer; a row altered; a delete method reachable | H29: Governance Architecture · BR-8.1 | I29: B.4 — no registry row
A30: C-6.5.2 | B30: I Conformance | C30: 6.5 The Ledger | D30: Row schema is the ratified 17-field schema; frozen as a contract | E30: B-M10-Q1 ruling | F30: V6 | G30: A schema with a field added or removed outside ceremony
A31: C-6.5.3 | B31: I Conformance | C31: 6.5 The Ledger | D31: Refused operations produce rows on the same terms as accepted | E31: BR-8.1; DAP-15 | F31: V3 | G31: A refusal with no row | H31: Governance Architecture · BR-8.1; DAP Backend spec · DAP-15
A32: C-6.5.4 | B32: I Conformance | C32: 6.5 The Ledger | D32: Metered event written before the result returns; if unwritable, no result | E32: DAP-21; DAP-29 | F32: V3 + V5 | G32: A result returned with no prior event under injected write failure | H32: DAP Backend spec · DAP-21; DAP Backend spec · DAP-29
A33: C-6.5.5 | B33: I Conformance | C33: 6.5 The Ledger | D33: Verifier runs under credentials the writer does not hold; writes to its own append-only store; publishes head hash to the tenant endpoint | E33: B-M10-Q2 ruling; C3 principle | F33: V2 + V3 | G33: A shared credential; verifier receipts inside the Ledger it verifies | I33: C3 — no registry row
A34: C-6.5.6 | B34: I Conformance | C34: 6.5 The Ledger | D34: Chain break raises SEV-1 and records a Watch signal, never an action | E34: B-M10-Q2 ruling | F34: V5 | G34: A break that neither pages nor signals; a break that triggers an action
A35: C-6.5.7 | B35: I Conformance | C35: 6.5 The Ledger | D35: au_3b_defensible coupled to at.source == reliable; False until a reliable time source exists | E35: R-C2; B-M10-Q1 | F35: V1 | G35: A record marked defensible with no reliable time source
A36: C-6.6.1 | B36: I Conformance | C36: 6.6 The Rules Service | D36: No rule takes effect without proposal, impact record, countersign, countdown, apply, re-verify | E36: RBM-7, RBM-8 | F36: V4 | G36: A rule in force with an incomplete ceremony record | H36: Rules Service spec · RBM-7; Rules Service spec · RBM-8
A37: C-6.6.2 | B37: I Conformance | C37: 6.6 The Rules Service | D37: Countdown cannot be shortened; Watch and Slow tiers cannot be applied by one principal, including under break-glass | E37: RBM-8; SER C.5 I-4 | F37: V5 | G37: A countdown cut short; a TCB-tier rule applied on one signature | H37: Rules Service spec · RBM-8
A38: C-6.6.3 | B38: I Conformance | C38: 6.6 The Rules Service | D38: Slowest tier requires a witness holding no credential over the component changed | E38: Doc 3 C3; R-16 | F38: V4 | G38: A witness who is also an operator of the changed component | I38: Doc 3 C3 — no registry row
A39: C-6.6.4 | B39: I Conformance | C39: 6.6 The Rules Service | D39: Every rule carries an ROC-compliant identifier and class | E39: ROC-1 to ROC-11 | F39: V7 | G39: A rule with a positional-only ID outside its document scope | H39: ROC spec · ROC-1; ROC spec · ROC-2; ROC spec · ROC-3; ROC spec · ROC-4; ROC spec · ROC-5; ROC spec · ROC-6; ROC spec · ROC-7; ROC spec · ROC-8; ROC spec · ROC-9; ROC spec · ROC-10; ROC spec · ROC-11
A40: C-6.6.5 | B40: I Conformance | C40: 6.6 The Rules Service | D40: Fallback-era determinations carry controlled_determination_basis and the flag cannot be flipped | E40: R-C1 | F40: V1 | G40: A fallback determination without the marker, or the marker mutable
A41: C-6.7.1 | B41: I Conformance | C41: 6.7 The Data Access Portal | D41: Exactly six crossing profiles; no operation moves data out that maps to none of them | E41: DAP-6 to DAP-11 | F41: V2 + V7 | G41: A seventh route; an entitlement mode that collapses profiles | H41: DAP Backend spec · DAP-6; DAP Backend spec · DAP-7; DAP Backend spec · DAP-8; DAP Backend spec · DAP-9; DAP Backend spec · DAP-10; DAP Backend spec · DAP-11
A42: C-6.7.2 | B42: I Conformance | C42: 6.7 The Data Access Portal | D42: A controlled request routes to the named approving authority and does not execute while pending | E42: DAP-14 | F42: V5 | G42: Execution beginning before the decision | H42: DAP Backend spec · DAP-14
A43: C-6.7.3 | B43: I Conformance | C43: 6.7 The Data Access Portal | D43: Silence expires a request unexecuted; expiry at 14 days with working-day roll-forward; Expired offers Submit again as a new request | E43: DAP-15; ruling 20 Sep 2026 | F43: V1 + V6 | G43: A request proceeding by default; an expired request reopened | H43: DAP Backend spec · DAP-15
A44: C-6.7.4 | B44: I Conformance | C44: 6.7 The Data Access Portal | D44: Decisions record the deciding identity and reason; the approver is never surfaced to the requester | E44: DAP-15 | F44: V3 + V6 | G44: A decision row without identity; an approver name on the party surface | H44: DAP Backend spec · DAP-15
A45: C-6.7.5 | B45: I Conformance | C45: 6.7 The Data Access Portal | D45: Raw download: redaction runs as a gate per unit; every unit individually recorded; sign-off recorded | E45: DAP-11 | F45: V5 + V3 | G45: A partial release after redaction failure; a release without per-unit rows | H45: DAP Backend spec · DAP-11
A46: C-6.7.6 | B46: I Conformance | C46: 6.7 The Data Access Portal | D46: Every release is debited against the release budget; exceeding it refuses | E46: DAP-35 | F46: V1 + V5 | G46: A release exceeding the ceiling; no debit row | H46: Amendment W-7 · DAP-35
A47: C-6.7.7 | B47: I Conformance | C47: 6.7 The Data Access Portal | D47: No Blocked reason for kind estate quantifies, compares, or implies remaining budget | E47: DAP-35; FE brief §4 | F47: V6 | G47: A reason line that leaks how much budget is left | H47: Amendment W-7 · DAP-35
A48: C-6.7.8 | B48: I Conformance | C48: 6.7 The Data Access Portal | D48: A trained artefact does not egress until the distance probe passes on an SFP-8-conforming path | E48: DAP-31, DAP-31+ | F48: V1 + V5 | G48: Egress without a probe row; a probe on an unverified serving path | H48: Amendment T-1 · DAP-31; Amendment T-1 · DAP-31 | I48: DAP-31+ — extension not registered as its own row (base DAP-31 is)
A49: C-6.7.9 | B49: I Conformance | C49: 6.7 The Data Access Portal | D49: Entering models pass the admission battery before contact with any estate data | E49: DAP-32, DAP-32+ | F49: V5 | G49: A model touching estate data before battery completion | H49: Amendment T-2 · DAP-32; Amendment T-2 · DAP-32 | I49: DAP-32+ — extension not registered as its own row (base DAP-32 is)
A50: C-6.7.10 | B50: I Conformance | C50: 6.7 The Data Access Portal | D50: Fine-tuning is differentially private unless the licence and owner explicitly opt out | E50: DAP-36 | F50: V1 | G50: A training run without DP and without an opt-out record | H50: Amendment W-8 · DAP-36
A51: C-6.7.11 | B51: I Conformance | C51: 6.7 The Data Access Portal | D51: Rights withdrawal triggers re-derivation or recall of every artefact citing the unit | E51: DAP-38 | F51: V3 + V5 | G51: A withdrawn unit still cited by a live artefact | H51: Pruning & Unlearning Amendment · DAP-38
A52: C-6.7.12 | B52: I Conformance | C52: 6.7 The Data Access Portal | D52: Blocked is exactly three kinds; Interrupted is non-terminal with bounded, receipted auto-retry | E52: Q7 ruling | F52: V6 + V1 | G52: A fourth Blocked kind; an unbounded retry
A53: C-6.7.13 | B53: I Conformance | C53: 6.7 The Data Access Portal | D53: Every retrieval writes a metered event per download | E53: DAP-21; lifecycle wave | F53: V3 | G53: A download with no event | H53: DAP Backend spec · DAP-21
A54: C-6.8.1 | B54: I Conformance | C54: 6.8 The principal model | D54: Three principal kinds; an individual or agent cannot exist without an organisation | E54: PRIN-1 | F54: V2 | G54: An orphan principal | H54: principal_model_v1 · PRIN-1
A55: C-6.8.2 | B55: I Conformance | C55: 6.8 The principal model | D55: No principal self-admits; admission is by named authority | E55: PRIN-2 | F55: V5 | G55: An admission with no admitting authority | H55: principal_model_v1 · PRIN-2
A56: C-6.8.3 | B56: I Conformance | C56: 6.8 The principal model | D56: Credential material is never persisted readable; issue and revoke only | E56: PRIN-6 | F56: V2 + V5 | G56: A read path returning credential material | H56: principal_model_v1 · PRIN-6
A57: C-6.8.4 | B57: I Conformance | C57: 6.8 The principal model | D57: Every record carries a trust-domain identifier; a write without one refuses | E57: PRIN-9, PRIN-10 | F57: V5 | G57: A record defaulted to the estate's domain | H57: principal_model_v1 · PRIN-9; principal_model_v1 · PRIN-10
A58: C-6.8.5 | B58: I Conformance | C58: 6.8 The principal model | D58: Ledger actor populated only from propagated context; a write with no principal in context fails closed | E58: PRIN-11, PRIN-12 | F58: V2 + V5 | G58: A caller-supplied actor string; an empty-actor write succeeding | H58: principal_model_v1 · PRIN-11; principal_model_v1 · PRIN-12
A59: C-6.8.6 | B59: I Conformance | C59: 6.8 The principal model | D59: Principal context is read-only in flight | E59: PRIN-13 | F59: V2 | G59: A service substituting the principal it was given | H59: principal_model_v1 · PRIN-13
A60: C-6.9.1 | B60: I Conformance | C60: 6.9 Serving integrity | D60: Same registered artefact, same input, same seed → same output regardless of memory placement or load | E60: serving_integrity_v1 A20.15; SFP-8 | F60: V1 | G60: Output varying with placement or pressure | H60: serving_integrity_v1 · A20.15; serving_integrity_v1 · SFP-8
A61: C-6.9.2 | B61: I Conformance | C61: 6.9 Serving integrity | D61: Artefact hash verified at load; token-exact reproduction check on schedule; refuse if unverifiable | E61: SFP-8 | F61: V5 | G61: A model served with an unverified hash | H61: serving_integrity_v1 · SFP-8
A62: C-6.9.3 | B62: I Conformance | C62: 6.9 Serving integrity | D62: Acceptance verdicts (MOAC, yield wall, probes) valid only from a conforming path | E62: TGT+; DAP-31+/32+ | F62: V4 | G62: A verdict recorded from a non-conforming path | H62: Amendment T-1 · DAP-31 | I62: DAP-31+ — extension not registered as its own row (base DAP-31 is)
A63: C-6.10.1 | B63: I Conformance | C63: 6.10 Memory compaction | D63: The Ledger, receipts, provenance, and audit log are never compacted | E63: MEM-1 | F63: V2 | G63: A compaction path touching the record | H63: memory_compaction_v1 · MEM-1
A64: C-6.10.2 | B64: I Conformance | C64: 6.10 Memory compaction | D64: Retention decided by the ratified deterministic rule set; a learned component drafts only | E64: MEM-3 | F64: V2 + V1 | G64: A model deciding what is retained | H64: memory_compaction_v1 · MEM-3
A65: C-6.10.3 | B65: I Conformance | C65: 6.10 Memory compaction | D65: Facts kept by hash pointer, never rewritten; receipts and refusals kept by reference | E65: MEM-3 | F65: V1 | G65: A paraphrased fact in a compacted artefact | H65: memory_compaction_v1 · MEM-3
A66: C-6.10.4 | B66: I Conformance | C66: 6.10 Memory compaction | D66: Compaction writes a Ledger row with a loss statement before the artefact is readable | E66: MEM-6 | F66: V3 + V5 | G66: A readable artefact with no row | H66: memory_compaction_v1 · MEM-6
A67: C-6.10.5 | B67: I Conformance | C67: 6.10 Memory compaction | D67: Reload is deterministic and states depth lost; unverifiable hash refuses | E67: MEM-7, MEM-8 | F67: V1 + V5 | G67: A reload re-summarising; a reload without the loss statement | H67: memory_compaction_v1 · MEM-7; memory_compaction_v1 · MEM-8
A68: C-6.10.6 | B68: I Conformance | C68: 6.10 Memory compaction | D68: Erasure reaches compacted memory and overrides retention lengthening | E68: MEM-9 | F68: V5 | G68: A withdrawn unit surviving in a compacted artefact | H68: memory_compaction_v1 · MEM-9
A69: C-6.11.1 | B69: I Conformance | C69: 6.11 Entitlement | D69: Resolution inside the chokepoint: principal → licence → row → dial → allowance; any missing link refuses | E69: ENT-16 | F69: V5 | G69: A call proceeding with a default licence or allowance | H69: entitlement_service_v1 · ENT-16
A70: C-6.11.2 | B70: I Conformance | C70: 6.11 Entitlement | D70: Resolution is a pure function with no learned parameter | E70: ENT-17 | F70: V2 | G70: A model output reachable by the resolver | H70: entitlement_service_v1 · ENT-17
A71: C-6.11.3 | B71: I Conformance | C71: 6.11 Entitlement | D71: Allowance recomputed from Ledger events; no stored counter | E71: ENT-22 | F71: V2 + V3 | G71: A balance store that can drift from events | H71: entitlement_service_v1 · ENT-22
A72: C-6.11.4 | B72: I Conformance | C72: 6.11 Entitlement | D72: Exhaustion serves locally with the fixed string, never silently; never refuses when local can serve | E72: ENT-26 | F72: V6 + V5 | G72: A local fallback without the string; a refusal with a local row available | H72: entitlement_service_v1 · ENT-26
A73: C-6.11.5 | B73: I Conformance | C73: 6.11 Entitlement | D73: A reseller-frontier row cannot be listed without an agreement record | E73: ENT-32 | F73: V4 | G73: A listed row with no agreement on record | H73: entitlement_service_v1 · ENT-32
A74: C-6.11.6 | B74: I Conformance | C74: 6.11 Entitlement | D74: Customer keys: never displayable; every call still passes the custody sequence | E74: ENT-35, ENT-37 | F74: V2 + V5 | G74: A key readable after entry; a masked-send skipped on a customer key | H74: entitlement_service_v1 · ENT-35; entitlement_service_v1 · ENT-37
... A83: C-6.12.7 | B83: I Conformance | C83: 6.12 Content registry and salience | D83: Unsupported claims are refused, not softened | E83: CON-24 | F83: V5 | G83: A hedged sentence displaying where an anchor is absent | H83: content_registry_v1 · CON-24
A84: C-6.12.8 | B84: I Conformance | C84: 6.12 Content registry and salience | D84: No store of rendered templated text; no draft, approval, or publish state | E84: CON-25; LIM-3 | F84: V2 | G84: A CMS-shaped table | H84: content_registry_v1 · CON-25 | I84: LIM-3 — no registry row
A85: C-6.13.1 | B85: I Conformance | C85: 6.13 Frontends — governance in the client | D85: Approval blocks execution; the client shows a blocked state, not a spinner or a dismissible warning | E85: DAP-14; UI brief §5 | F85: V6 + V5 | G85: A UI proceeding provisionally while approval is pending | H85: DAP Backend spec · DAP-14
A86: C-6.13.2 | B86: I Conformance | C86: 6.13 Frontends — governance in the client | D86: Silence never approves; expired requests render as expired, never auto-approved | E86: DAP-15 | F86: V6 | G86: An expired request shown as approved or vanished | H86: DAP Backend spec · DAP-15
A87: C-6.13.3 | B87: I Conformance | C87: 6.13 Frontends — governance in the client | D87: The chat proposes and never decides: no path from chat to approval, scope change, or gate bypass | E87: DAP-20 | F87: V2 | G87: A chat action that executes or widens scope | H87: DAP Backend spec · DAP-20
A88: C-6.13.4 | B88: I Conformance | C88: 6.13 Frontends — governance in the client | D88: Fixed strings render verbatim; a substitution rule matching nothing is RED | E88: FE brief §0.2 | F88: V6 | G88: A reworded fixed string
A89: C-6.13.5 | B89: I Conformance | C89: 6.13 Frontends — governance in the client | D89: Every number derives from a verified field or renders “not yet measured” | E89: FE brief §2.1 | F89: V6 | G89: A figure with no backing field
A90: C-6.13.6 | B90: I Conformance | C90: 6.13 Frontends — governance in the client | D90: Browse renders aggregates only; no code path surfaces unit content | E90: DAP-6 | F90: V2 | G90: A record preview reachable from Browse | H90: DAP Backend spec · DAP-6
A91: C-6.13.7 | B91: I Conformance | C91: 6.13 Frontends — governance in the client | D91: Redaction is not a requester-controlled setting on the raw-download screen | E91: DAP-11 | F91: V6 | G91: A redaction-level control on the party surface | H91: DAP Backend spec · DAP-11
A92: C-6.14.1 | B92: I Conformance | C92: 6.14 Agent and swarm containment | D92: Four ceilings are unconditional and non-admissible by any ceremony: no self-replication, resource acquisition, credential escalation, oversight tampering | E92: AC-1; watch_learning_v1 A20.16 | F92: V2 + V5 | G92: A capability class admitting a ceiling | H92: Agent Containment spec · AC-1; watch_learning_v1 · A20.16
A93: C-6.14.2 | B93: I Conformance | C93: 6.14 Agent and swarm containment | D93: Scope expands only by track record plus ratification by a party independent of the operator; the runtime proposes, never advances | E93: AC-2; R-18 effect 6 | F93: V4 + V5 | G93: A rung advanced on the runtime's check alone | H93: Agent Containment spec · AC-2
A94: C-6.14.3 | B94: I Conformance | C94: 6.14 Agent and swarm containment | D94: Every action cites an admitted capability class with a certificate; first exercise triggers the foundation floor and the research queue | E94: AC-17, AC-18; watch_learning_v1 A20.16 | F94: V3 | G94: An action with no admitted class | H94: watch_learning_v1 · AC-17; watch_learning_v1 · AC-18; watch_learning_v1 · A20.16
A95: C-6.14.4 | B95: I Conformance | C95: 6.14 Agent and swarm containment | D95: Coalitions evaluated jointly; aggregate effect bounded regardless of detection | E95: AC-10; DAP-34 | F95: V1 | G95: A coalition bounded only by a member allow-list | H95: Agent Containment spec · AC-10; Amendment W-4 · DAP-34
A96: C-6.14.5 | B96: I Conformance | C96: 6.14 Agent and swarm containment | D96: Contained agents are served under SFP-8; contain is a session freeze | E96: AC-13, AC-14 | F96: V5 | G96: A contained agent served on an unverified path | H96: serving_integrity_v1 · AC-13; serving_integrity_v1 · AC-14
A97: C-6.15.1 | B97: I Conformance | C97: 6.15 Data protection and retention | D97: Breach notification path exists and is exercised within 72 hours in a drill record | E97: Kenya DPA 2019; Pilot Agreement cl. 7.2 | F97: V4 + V5 | G97: No drill record; a path exceeding 72 hours
A98: C-6.15.2 | B98: I Conformance | C98: 6.15 Data protection and retention | D98: Erasure overrides retention lengthening in every store that holds derived content | E98: MEM-9; CON-27; DAP-38 | F98: V5 | G98: A retention setting blocking a lawful erasure | H98: memory_compaction_v1 · MEM-9; content_registry_v1 · CON-27; Pruning & Unlearning Amendment · DAP-38
A99: C-6.15.3 | B99: I Conformance | C99: 6.15 Data protection and retention | D99: Retention defaults recorded per collection; tenants may lengthen, not shorten, save for erasure | E99: D-14 | F99: V7 | G99: A collection with no recorded retention | I99: D-14 — no registry row
A100: C-6.16.1 | B100: I Conformance | C100: 6.16 Product function | D100: The system is built and started from the audit target by documented steps only; each engine named in Build Status §1 (SyniSense, Solva, Northena, Mtafiti, Targeta, Mkondo), the Watch and the Ledger answers a health request | E100: Build Status §1; ORCH_BOOT.md | F100: V8 | G100: An engine that does not start; a step required that no document states. A component that does not exist is NOT BUILT
A101: C-6.16.2 | B101: I Conformance | C101: 6.16 Product function | D101: O1 Custody (#1–#4 · Docs 1, 2): a request carrying an entity on the tenant confidentiality list crosses; the payload captured at the perimeter contains no listed entity; both custody pathways leave a receipt | E101: Doc 1 A5.1, A5.2, A5.7, A5.8; Doc 2 A5.1 | F101: V8 + rule class | G101: A listed entity in the captured payload; a crossing with no receipt
A102: C-6.16.3 | B102: I Conformance | C102: 6.16 Product function | D102: O3 Reasoning and grounding (#8, #31 · Doc 4): a question whose answer the estate does not contain is refused, not answered; the lower-rung fallback reproduces byte-identically | E102: Doc 1 A5.9; Doc 4 A5.2, A5.3 | F102: V8 + rule class | G102: An ungrounded answer returned; a fallback output that drifts
A103: C-6.16.4 | B103: I Conformance | C103: 6.16 Product function | D103: O4 Direction and focus (#16–#18 · Docs 5, 6): the objective captured at the start of a long session is present and unaltered at its end; scope expands only by explicit request | E103: Doc 1 B5.3; Doc 5; Doc 6 A5.2, A5.3 | F103: V8 + rule class | G103: An objective edited or lost in flight; scope widened with no request recorded
A104: C-6.16.5 | B104: I Conformance | C104: 6.16 Product function | D104: O5 Context preservation (#19–#21 · Docs 7, 8): every unit carries a re-extraction handle; an on-demand fetch is served without re-running the estate | E104: Doc 7 A5.2; Doc 8 A5.2, A5.3 | F104: V8 + rule class | G104: A unit with no handle; a fetch that triggers an estate run
A105: C-6.16.6 | B105: I Conformance | C105: 6.16 Product function | D105: O6 Estate registry (#12–#15 · Docs 9, 10): each source type the build claims connects to a reference instance; the census of a fixture of known composition matches it; an audio fixture is read | E105: Doc 9 A5.2, A5.3; Doc 10 | F105: V8 + rule class | G105: A claimed connector that fails; a census that differs from the fixture
A106: C-6.16.7 | B106: I Conformance | C106: 6.16 Product function | D106: O7 Cost and compute (#9–#11 · Docs 11, 12): cost is shown before commit and is a measured figure; a pull-seam job completes with no estate data leaving | E106: Doc 11 A5.3; Doc 12 A5.2 | F106: V8 + rule class | G106: A job committing with no prior cost; a simulated cost; estate data in the outbound capture
A107: C-6.16.8 | B107: I Conformance | C107: 6.16 Product function | D107: O8 Training and models (#22–#25, #30 · Docs 13, 14, 17, 20): one training job runs end to end on a fixture — objective dialogue, mission reflected then frozen, run, acceptance against a registered baseline | E107: Doc 13 A5.2, A5.3; Doc 14; Doc 17; Doc 20 | F107: V8 + rule class | G107: A job that completes with no frozen mission; acceptance against an unregistered baseline
A108: C-6.16.9 | B108: I Conformance | C108: 6.16 Product function | D108: O9 Orchestration (#27, #32 · Doc 15): a job follows the specified path to completion; a rule-book change takes effect only by ceremony | E108: Doc 15 | F108: V8 + rule class | G108: A job completing off-path; a rule book edited in place
...

Sheet Registry Defects
A1: Ref | B1: Artefact | C1: Defect observed at issue of v2 | D1: Measure | E1: Effect on the audit if left | F1: Owner action | G1: State
A2: RD-01 | B2: Master Registry · Status | C2: 349 of 602 rules are PROPOSED or DEFAULT, including every rule prefixed DAP, ENT, CON, PRIN, MEM, AC, RBM, BR, SEC, SFP, FP, TD, DET and I. Of the 89 registry rules Standards v1 §6 names, 2 are CANON or RULED (Doc 1 A5.1, Doc 1 A5.7). | D2: CANON 142 · RULED 16 · PROPOSED/DEFAULT 349 · OPEN 25 · outside vocabulary 70 | E2: Under v1 the domain passes §6.2 and §6.5–§6.14 could return only NOT YET RATIFIED. Either the Status column is stale or the newest work is unratified; the registry cannot say which. | F2: Confirm the Status column against DECISIONS.md before the audit target is tagged. v2 removes the dependency: every rule is examined and given a verdict whatever its status; status sets weight only. | G2: OPEN
A3: RD-02 | B3: Master Registry · Status | C3: 70 rows carry a status outside the vocabulary: “—” 27 (14 of them Doc 3, the Watch), “See xlsx” 25, “OWNER-DIRECTED → CANON” 14, “— (see heading)” 3, “DETERMINED” 1. | D3: 70 rows | E3: Weight cannot be set. Promise #6 rests on 14 such rows and nothing else. | F3: Rule each in the Status Map sheet, columns B and C. | G3: OPEN
A4: RD-03 | B4: Master Registry · Statement and class | C4: For all 232 rows from Docs 1–20 the Statement column holds the rule’s heading (Legend sheet says so). The v1 verification class was derived from that heading. All 158 CANON and RULED rules are heading-only; 139 of them fell to V7, document inspection. | D4: 232 heading-only · 158 COUNTS · 139 of those V7 | E4: The ratified core would be audited by reading documents. “The single chokepoint” is V7 in the sheet and V2 in Standards §6.3. | F4: Transcribe full rule text into the registry, or accept Standards 2.4: the auditor reads the text at Source file:line and re-derives the class. Column Q marks every provisional class. | G4: OPEN
A5: RD-04 | B5: Master Registry vs Standards §6 | C5: Of 89 rules named in §6, 48 carry a sheet class that is not among the classes §6 requires for them. | D5: 48 of 89 | E5: The auditor is told two different evidence standards for the same rule. | F5: Closed in v2: column O carries the §6 class and governs (class precedence, QA Legend). | G5: CLOSED
A6: RD-05 | B6: Standards v1 §6 · citations | C6: Standards cited as governing do not resolve to a registry row: Doc 0 BA-1.1, Doc 3 A2, Doc 3 A3, Doc 3 C3, B.4, B.8, D-14, LIM-3, DAP-31+, DAP-32+. | D6: 10 identifiers | E6: A check with no locatable rule cannot be verified against canon. | F6: Register the rules, or correct the citations. Check Register column I lists them per check. | G6: OPEN
A7: RD-06 | B7: Standards v1 §6.2 · citation | C7: The golden-input check cites DET-1 and DET-2. In the registry DET-1 is an OPEN item on a CIF halt mechanism and DET-2 concerns a Mtafiti classification step. | D7: 2 identifiers | E7: The TCB determinism check points at rules that say something else. | F7: Supply the correct identifiers. Until then C-6.2.2 is verified against tcb_enumeration_v1 and the determinism inventory text. | G7: OPEN
A8: RD-07 | B8: Promise Registry · security promises | C8: The 33 security assurance promises have no fulfilling-rule column. The text of S-1 to S-25 sits in Security_Assurance_Promise_Set.xlsx, which was not issued with the registries. | D8: 33 promises · 25 without text | E8: Promise roll-up cannot be computed for any security promise. | F8: Issue the workbook (Standards 9.1) and confirm the mapping proposed in Promise Registry v2, sheet Promise–Rule Map, which is drawn only from identifiers the promise rows themselves name. | G8: OPEN
A9: RD-08 | B9: Promise Registry · canon promises | C9: Promises #6, #25 and #26 have no CANON or RULED fulfilling rule. Promises #5, #28 and #29 have no rule at all (the Objectives sheet explains #5 and #29 as composite theorems of Doc 16; #28 is unexplained). | D9: 6 of 32 | E9: Under v1 these were vacuously HELD or undefined. | F9: v2 verdicts NO COUNTABLE RULES and ABSENT. Owner to explain #28. | G9: OPEN
A10: RD-09 | B10: Master Registry · sampling tier | C10: 110 of the 158 CANON and RULED rules were Tier B, sampled at 30%, while a promise is HELD only if every one passes. | D10: 110 of 158 | E10: A promise could be declared HELD on a third of its rules. | F10: Closed in v2: column R places every COUNTS rule in Tier A. | G10: CLOSED
A11: RD-10 | B11: Counts across artefacts | C11: Standards v1 states 595 rules and 299 Tier A; the registry holds 602 and 306; Build Status totals 589; the Legend sheet says 286 and says the S-series and RBM rules are not included, though both are. | D11: 595 / 602 / 589 / 286 | E11: The auditor cannot confirm it holds the version the Standards describe. | F11: Refresh Build Status and Legend. v2 pins the registry by hash in the Audit Order. | G11: OPEN
A12: RD-11 | B12: Master Registry · Build Status | C12: Sections 2–4 list as missing documents the registry carries rows from: security_architecture_v1, determinism_inventory_v1, failure_posture_v1, trust_domains_v1, handoff_registry_v1, business_continuity_v1. | D12: 6 documents | E12: The builder’s own status sheet contradicts the registry it ships in. | F12: Refresh Build Status, or mark it superseded. | G12: OPEN
... A17: RD-16 | B17: Master Registry · extraction damage | C17: Two Deck Engine statements are fragments: DR-R10 “–R11)” and DR-R13 “)”. | D17: 2 rows | E17: The rules cannot be read. | F17: Re-extract. | G17: OPEN

Sheet QA Legend
A1: Class | B1: Name | C1: Evidence standard | D1: Derivation pattern (first match, in this order)
A2: V1 | B2: Test evidence | C2: Golden-input, byte-identical output; RED-first test ID; ratchet manifest entry | D2: determinist|byte-identical|golden|hash|signature|signed|reproduc|same output|token-exact|seed
A3: V2 | B3: Structural evidence | C3: Negative-scan or AST rule present, named, and green in CI; scan surface stated | D3: MUST NOT|must not|no code path|exactly one|only .* may|never (be|is|are)? ?(invoked|called|written|read|reach)|negative[- ]scan|sole importer|no path
A4: V5 | B4: Failure-injection demonstration | C4: Dependency made unreachable or check made to error; observed refusal; no result returned; stale marker where degradation is the ruled posture | D4: fail[- ]closed|refuse|refusal|unreachable|cannot complete|errors|does not proceed|not permitted to have occurred
A5: V3 | B5: Record evidence | C5: Ledger rows inspected; hash-chain verifier receipt; refused operations present on identical terms | D5: receipt|[Ll]edger|recorded|metered event|written before|append-only|hash-chain
A6: V4 | B6: Governance-record evidence | C6: DECISIONS.md entry; ceremony record with tier, countersign, countdown, apply, re-verify; canon_ref present | D6: ceremony|countersign|ratif|ruling|witness|DECISIONS|canon_ref|ratchet
A7: V6 | B7: Surface inspection | C7: DOM-bound substitution rule or harness receipt; fixed string verbatim; honest-gap variant rendered on null | D7: surface|render|display|string|badge|card|picker|toast|notification
A8: V7 | B8: Document & design inspection | C8: Specification text against implementation description; provenance sections; objective card lines. Floor only: insufficient wherever a stronger class could apply. | D8: — (no pattern matched)
A10: Tier A | B10: 100% examined | C10: Any rule with primary or effective class V1, V2 or V5; any rule with prefix AC, BR, DET, FP, G, I, PRIN, RBM, ROC, S, SEC, SFP, TD; any rule in Docs 1, 3, 4, 5; and — new at v2 — every rule whose weight is COUNTS (CANON or RULED), because a promise cannot be rolled up over rules that were not examined. Column R 'Effective tier' computes this; column G is the v1 tier, kept for reference.
A11: Tier B | B11: Sample ≥ 30% | C11: All other rules. Sample drawn per source document by the seeded method in Standards 5.2. Any FAIL in a sample escalates that rule's document to 100%.
A12: V8 | B12: Functional demonstration | C12: An end-to-end scenario the auditor runs on a system stood up from the audit target: stated input, behaviour the rule text requires, observed output. Required in addition to the primary class for every COUNTS rule in the product domains (Standards 6.16). | D12: — (assigned by Standards 6.16, not by pattern)
A13: Class precedence | B13: Which class applies | C13: 1. The class stated for the rule in Standards §6 (column O). 2. The class derived from the rule’s full text at its source file:line. 3. The class in column D, which for HEADING ONLY rows was derived from a heading and is provisional. The auditor may raise a class with a written reason and never lowers one.
A14: Rule verdict | B14: Five, status-independent | C14: PASS · FAIL · NOT BUILT · NOT VERIFIABLE · NOT EXAMINED. NOT EXAMINED is permitted only for weight OPEN or a Tier B rule not drawn, and carries its reason in column W. NOT YET RATIFIED is withdrawn as a verdict: ratification sets weight (column L), it does not replace the finding.
A15: Weight | B15: Set by status, not by the auditor | C15: COUNTS (CANON, RULED) · UNRATIFIED (PROPOSED, DEFAULT) · OPEN · UNDEFINED (status outside the vocabulary — owner action in Status Map).
A16: Cell colours | C16: Yellow = auditor or owner input. Grey = formula; do not overwrite.

Sheet System Rules Registry
A1: Rule ID | B1: Statement | C1: Objective | D1: Promise / Source Document | E1: Doc | F1: Status | G1: Enforcement Class | H1: Domain | I1: Source (file:line) | J1: Relationship | K1: Builder Status
A2: A5.1 | B2: The single chokepoint | C2: O1 Custody & Confidentiality | D2: #1 — NO LEAKAGE OF CONFIDENTIAL INFORMATION | E2: Doc 1 | F2: CANON | H2: SyniSense | I2: 01_Custody_and_the_Crossing_Part_1_The_Chokepoint.md:67 | J2: Base canon
A3: A5.2 | B3: The custody sequence | C3: O1 Custody & Confidentiality | D3: #1 — NO LEAKAGE OF CONFIDENTIAL INFORMATION | E3: Doc 1 | F3: CANON | H3: SyniSense | I3: 01_Custody_and_the_Crossing_Part_1_The_Chokepoint.md:69 | J3: Base canon
A4: A5.3 | B4: The per-request envelope does not outlive the call | C4: O1 Custody & Confidentiality | D4: #1 — NO LEAKAGE OF CONFIDENTIAL INFORMATION | E4: Doc 1 | F4: CANON | H4: SyniSense | I4: 01_Custody_and_the_Crossing_Part_1_The_Chokepoint.md:77 | J4: Base canon
A5: A5.4 | B5: Tenant-scoped entity resolution | C5: O1 Custody & Confidentiality | D5: #1 — NO LEAKAGE OF CONFIDENTIAL INFORMATION | E5: Doc 1 | F5: CANON | H5: SyniSense | I5: 01_Custody_and_the_Crossing_Part_1_The_Chokepoint.md:81 | J5: Base canon
A6: A5.5 | B6: The outbound network is closed except at the crossing | C6: O1 Custody & Confidentiality | D6: #1 — NO LEAKAGE OF CONFIDENTIAL INFORMATION | E6: Doc 1 | F6: CANON | H6: SyniSense | I6: 01_Custody_and_the_Crossing_Part_1_The_Chokepoint.md:83 | J6: Base canon
A7: A5.6 | B7: Structural impossibility, not policed prohibition | C7: O1 Custody & Confidentiality | D7: #1 — NO LEAKAGE OF CONFIDENTIAL INFORMATION | E7: Doc 1 | F7: CANON | H7: SyniSense | I7: 01_Custody_and_the_Crossing_Part_1_The_Chokepoint.md:89 | J7: Base canon
A8: A5.7 | B8: The trust receipt | C8: O1 Custody & Confidentiality | D8: #1 — NO LEAKAGE OF CONFIDENTIAL INFORMATION | E8: Doc 1 | F8: CANON | H8: SyniSense | I8: 01_Custody_and_the_Crossing_Part_1_The_Chokepoint.md:91 | J8: Base canon
A9: A5.8 | B9: Two custody pathways, both receipted, neither bypassing the other | C9: O1 Custody & Confidentiality | D9: #1 — NO LEAKAGE OF CONFIDENTIAL INFORMATION | E9: Doc 1 | F9: CANON | H9: SyniSense | I9: 01_Custody_and_the_Crossing_Part_1_The_Chokepoint.md:101 | J9: Base canon
A10: A5.9 | B10: Grounding failure is a refusal, not a degraded answer | C10: O1 Custody & Confidentiality | D10: #1 — NO LEAKAGE OF CONFIDENTIAL INFORMATION | E10: Doc 1 | F10: CANON | H10: SyniSense | I10: 01_Custody_and_the_Crossing_Part_1_The_Chokepoint.md:103 | J10: Base canon
A11: A5.1 | B11: The list extends the tenant entity set consumed at the crossing | C11: O1 Custody & Confidentiality | D11: #2 — THE USER-EDITABLE CONFIDENTIALITY LIST | E11: Doc 2 | F11: CANON | H11: SyniSense | I11: 02_Custody_and_the_Crossing_Part_2_Confidentiality_and_Dual_File.md:65 | J11: Base canon
A12: A5.2 | B12: The objective-shaping loop produces a testable declaration | C12: O1 Custody & Confidentiality | D12: #2 — THE USER-EDITABLE CONFIDENTIALITY LIST | E12: Doc 2 | F12: PROPOSED | H12: SyniSense | I12: 02_Custody_and_the_Crossing_Part_2_Confidentiality_and_Dual_File.md:67 | J12: Base canon
A13: A5.3 | B13: Review shows reach against measured material only [CANON-adjacent] | C13: O1 Custody & Confidentiality | D13: #2 — THE USER-EDITABLE CONFIDENTIALITY LIST | E13: Doc 2 | F13: — | H13: SyniSense | I13: 02_Custody_and_the_Crossing_Part_2_Confidentiality_and_Dual_File.md:69 | J13: Base canon
... A603: SFP-7 | B603: | Reproduction Ceiling | Subjects: any artefact or output leaving a component boundary. Objects: controlled-unit content. Operations: egress, refuse. Rule: no artefact or output passes carrying reproduction of a controlled unit above the ruled threshold (DAP-31, A5.15). | | C603: O14 Governance Architecture — G-9 closure | D603: security_function_policies_v1 | E603: security_function_policies_v1 | F603: PROPOSED | H603: O14 Governance Architecture | I603: Security_Function_Policies_v1.docx | J603: Added at refresh 20 Sep 2026 (c) — surfaced by the audit-standards ID check

Sheet Objectives
A1: Objective → Promises
A3: Objective | B3: Promises / sources | C3: Rule count
A4: O1 Custody & Confidentiality | B4: #1 — NO LEAKAGE OF CONFIDENTIAL INFORMATION #2 — THE USER-EDITABLE CONFIDENTIALITY LIST #3 — INTENT, MEANING & QUESTION OBJECTIVE EXTRACTED BEFORE REDACTION #4 — THE DUAL-FILE RECORD | C4: 25
A5: O2 Security & Intent | B5: #26 — UNIVERSAL CONTAINMENT, AND THE ONE EXCEPTION #6 — THE ADAPTIVE, INTENT-MEASURING SECURITY AGENT #7 — INTENT MEASURED ACROSS LAYERS (Security Half) #7 — INTENT MEASURED WITHIN A REASONING SESSION (Reasoning Half) | C5: 25
A6: O3 Reasoning & Grounding | B6: #31 — THE SOPHISTICATED REASONING TOOL (SOLVA ITSELF) #8 — GUARDS AGAINST HALLUCINATION | C6: 12
A7: O4 Direction, Scope & Focus | B7: #16 — FOCUS MAINTAINED UNDER MASSIVE CONTEXT #17 — PROGRESSIVE DISCLOSURE #18 — OBJECTIVE PRESERVATION (Direction Half) | C7: 16
A8: O5 Context Preservation | B8: #19 — SHRINKAGE — CONTEXT PRESERVATION UNDER MASSIVE ESTATES #20 — THE SMALL MEMORY SERVICE THE MODEL READS FROM #21 — THE TRAFFIC CONTROLLER — ON-DEMAND FETCH WITHOUT RE-RUNNING THE ESTATE | C8: 15
A9: O6 Estate Registry | B9: #12 — CONNECTS TO ALL DATABASE TYPES #13 — THE CENSUS #14 — THE COMPREHENSIVE REGISTRY #15 — READS ANY DATA TYPE, INCLUDING AUDIO | C9: 22
A10: O7 Cost & Compute | B10: #10 — THE PULL SEAM — COMPUTE WITHOUT MOVING DATA OUT #11 — COST AT THE POINT OF REFLECTION, BEFORE COMMIT #9 — LOCAL-FIRST PROCESSING & THE CONSUMPTION LEVERS #9 — LOCAL-FIRST PROCESSING & THE CONSUMPTION LEVERS (Part B: consumption levers) | C10: 26
A11: O8 Training & Models | B11: #22 — AUTONOMOUS TRAINING, ANY OUTPUT DIMENSION #23 — THE OBJECTIVE-SHAPING DIALOGUE (specified first, because it precedes the job) #24 — THE PRETRAINED-MODEL BASELINE REGISTRY #25 — RETAINED LEARNING DATA & THE WHITE-PAPER PIPELINE #25 — White-Paper Pipeline (whitepaper_wizard_spec_v1) #30 — ALL LLMs, INCLUDING OPEN-WEIGHT, UNDER A SINGLE LICENSE Doc 17 — The Multidimensional Training Engine (extends #22–#24) Doc 20 — The Model Capability Register (extends #24, #30) Streaming Voice Training Capacity — proposed extension to Doc 17 §17.4a/§17.4c, NOT YET MERGED | C11: 86
A12: O9 Orchestration & Governance | B12: #27 — RULE BOOKS AND TEMPLATES, WRITTEN AND CHANGED BY CEREMONY #32 — WORKLOAD ORCHESTRATION — THE PATH OF SUCCESS FOR A JOB | C12: 9
A13: O10 Quality & Evidence | B13: Doc 19A — Critic Seam, Tier 1 deterministic checks (CANON, ratified 15 Jul 2026) Doc 19A — Critic Seam, behavioural rules (CANON, ratified 15 Jul 2026) Doc 19B — Evidence Protocol (PROPOSED, never confirmed adopted) | C13: 17
A14: O11 Skills & Rendering | B14: Deck Rendering Engine v1.0 Doc 18 — Callable Skill Files | C14: 22
A15: O12 Rule Governance | B15: rule_criteria_spec_v1 | C15: 11
A17: Cross-cutting (#5, #29 — Doc 16) | B17: No promise-level rules of their own — composite theorems over other promises. Doc 16 carries doctrine (§1–§12) and a 20-item ruling log, not rules. Excluded from count by design.

Sheet Legend
A1: System Rules Registry — Legend
A3: What this is | B3: The first population of the Rule Registry required by rule_criteria_spec_v1 ROC-10 — every individually-identified rule in the Akki canon, categorised objective → promise → rule. This is the retrofit OR-1 asked about, executed.
A5: Count | B5: 286 rules: 272 from Documents 1–20 and extensions (verified by extraction on 1 Sep 2026) plus ROC-1–11 (rule_criteria_spec_v1). Doc 16 excluded by design — see Objectives sheet.
A7: Statement column | B7: The rule's own heading as written in its source document (Docs 1–15, 17–20). For WPW and DR-R, the first sentence of the requirement. Full text lives in the source document at the cited line.
A9: Enforcement Class | B9: Deliberately blank. The 272 canon rules do not carry an enforcement-class tag today; assigning one per rule (ROC Axis 2) is the Rules Service's first assessment job, not something to infer from keywords here.
A11: Status | B11: Taken from the rule's own [TAG] where present. Docs 19A/19B: 19A rules are CANON (Critic Seam, ratified 15 Jul 2026); 19B (EP-x) are PROPOSED, never confirmed adopted. WPW: DEFAULT, R2 open. DR-R: OWNER-DIRECTED with four items strikeable. ROC: PROPOSED pending ratification.
A13: Not included | B13: Security assurance promises S-1–S-21 — they are promises awaiting rule decomposition, not rules. The Rules Service spec's own RBM-x requirements — a new document, to be registered on ratification.
A15: Source column | B15: file:line into the extracted canon text, so any row can be checked against its origin.
A17: QA v2 note | B17: This workbook is Master Requirements Registry v5 (sha256 00072c5829d3d89399cc5ca64661b405ac8a3cd0b43d0081f0d5f0bce109619d) with QA working sheets added on 21 Sep 2026: Audit Summary, Status Map, Check Register, Registry Defects, and columns K–X of QA Verification. Build Status, System Rules Registry, Objectives and the rows above on this sheet are unchanged; where they are stale (the count of 286 above; the total of 589 on Build Status) the discrepancy is logged in Registry Defects, not corrected here, because those are the builder’s statements.
